{"serverIp":"46.101.230.5","serverPort":"27960","gameEndTimestamp":1449325699,"matchStats":{"ABORTED":false,"CAPTURE_LIMIT":8,"EXIT_MSG":"Timelimit hit.","FACTORY":"ctf2","FACTORY_TITLE":"Capture The Flag ","FIRST_SCORER":"wam","FRAG_LIMIT":50,"GAME_LENGTH":1200,"GAME_TYPE":"CTF","INFECTED":0,"INSTAGIB":0,"LAST_LEAD_CHANGE_TIME":427925,"LAST_SCORER":"iceh","LAST_TEAMSCORER":"wam","MAP":"japanesecastles","MATCH_GUID":"5aa8f62c-2b1a-4e54-8d9a-fdc1c061ed3d","MERCY_LIMIT":0,"QUADHOG":0,"RESTARTED":0,"SCORE_LIMIT":150,"SERVER_TITLE":"#omega Quakenet CTF DE #1","TIME_LIMIT":20,"TRAINING":0,"TSCORE0":3,"TSCORE1":4},"playerStats":[{"ABORTED":false,"BLUE_FLAG_PICKUPS":5,"DAMAGE":{"DEALT":5370,"TAKEN":4140},"DEATHS":27,"HOLY_SHITS":0,"ITEM_TIMING":{"YELLOW_ARMOR":4662},"KILLS":35,"LOSE":0,"MATCH_GUID":"5aa8f62c-2b1a-4e54-8d9a-fdc1c061ed3d","MAX_STREAK":5,"MEDALS":{"ACCURACY":0,"ASSISTS":0,"CAPTURES":0,"COMBOKILL":0,"DEFENDS":8,"EXCELLENT":2,"FIRSTFRAG":0,"HEADSHOT":0,"HUMILIATION":0,"IMPRESSIVE":2,"MIDAIR":0,"PERFECT":0,"PERFORATED":0,"QUADGOD":0,"RAMPAGE":0,"REVENGE":1},"MODEL":"sarge","NAME":"^1sd^7-demon","NEUTRAL_FLAG_PICKUPS":0,"PICKUPS":{"AMMO":14,"ARMOR":10,"ARMOR_REGEN":0,"BATTLESUIT":0,"DOUBLER":0,"FLIGHT":0,"GREEN_ARMOR":0,"GUARD":0,"HASTE":0,"HEALTH":35,"INVIS":0,"INVULNERABILITY":0,"KAMIKAZE":0,"MEDKIT":0,"MEGA_HEALTH":0,"OTHER_HOLDABLE":0,"OTHER_POWERUP":0,"PORTAL":0,"QUAD":1,"RED_ARMOR":0,"REGEN":3,"SCOUT":0,"TELEPORTER":0,"YELLOW_ARMOR":8},"PLAY_TIME":900,"QUIT":1,"RANK":-1,"RED_FLAG_PICKUPS":0,"SCORE":263,"STEAM_ID":"76561197971572803","TEAM":1,"TEAM_JOIN_TIME":0,"TEAM_RANK":-1,"TIED_RANK":1,"TIED_TEAM_RANK":1,"WARMUP":false,"WEAPONS":{"BFG":{"D":0,"DG":0,"DR":0,"H":0,"K":0,"P":0,"S":0,"T":0},"CHAINGUN":{"D":0,"DG":0,"DR":0,"H":0,"K":0,"P":0,"S":0,"T":0},"GAUNTLET":{"D":0,"DG":0,"DR":0,"H":0,"K":0,"P":0,"S":0,"T":0},"GRENADE":{"D":0,"DG":100,"DR":28,"H":2,"K":1,"P":3,"S":7,"T":11},"HMG":{"D":0,"DG":0,"DR":0,"H":0,"K":0,"P":0,"S":0,"T":0},"LIGHTNING":{"D":0,"DG":0,"DR":0,"H":0,"K":0,"P":0,"S":0,"T":0},"MACHINEGUN":{"D":0,"DG":365,"DR":80,"H":73,"K":3,"P":0,"S":251,"T":324},"NAILGUN":{"D":0,"DG":0,"DR":0,"H":0,"K":0,"P":0,"S":0,"T":0},"OTHER_WEAPON":{"D":0,"DG":0,"DR":0,"H":0,"K":0,"P":0,"S":0,"T":0},"PLASMA":{"D":1,"DG":0,"DR":399,"H":0,"K":0,"P":7,"S":0,"T":6},"PROXMINE":{"D":0,"DG":0,"DR":0,"H":0,"K":0,"P":0,"S":0,"T":0},"RAILGUN":{"D":6,"DG":640,"DR":892,"H":8,"K":2,"P":14,"S":21,"T":96},"ROCKET":{"D":11,"DG":3120,"DR":1298,"H":56,"K":19,"P":27,"S":103,"T":331},"SHOTGUN":{"D":9,"DG":1145,"DR":1303,"H":201,"K":10,"P":26,"S":820,"T":130}},"WIN":0},{"ABORTED":false,"BLUE_FLAG_PICKUPS":0,"DAMAGE":{"DEALT":10335,"TAKEN":8511},"DEATHS":53,"HOLY_SHITS":0,"ITEM_TIMING":{"YELLOW_ARMOR":5562},"KILLS":56,"LOSE":0,"MATCH_GUID":"5aa8f62c-2b1a-4e54-8d9a-fdc1c061ed3d","MAX_STREAK":5,"MEDALS":{"ACCURACY":0,"ASSISTS":0,"CAPTURES":3,"COMBOKILL":2,"DEFENDS":8,"EXCELLENT":4,"FIRSTFRAG":1,"HEADSHOT":2,"HUMILIATION":0,"IMPRESSIVE":5,"MIDAIR":3,"PERFECT":0,"PERFORATED":0,"QUADGOD":0,"RAMPAGE":0,"REVENGE":7},"MODEL":"xaero/red","NAME":"wam","NEUTRAL_FLAG_PICKUPS":0,"PICKUPS":{"AMMO":24,"ARMOR":81,"ARMOR_REGEN":0,"BATTLESUIT":0,"DOUBLER":0,"FLIGHT":0,"GREEN_ARMOR":0,"GUARD":0,"HASTE":0,"HEALTH":84,"INVIS":0,"INVULNERABILITY":0,"KAMIKAZE":0,"MEDKIT":0,"MEGA_HEALTH":0,"OTHER_HOLDABLE":0,"OTHER_POWERUP":0,"PORTAL":0,"QUAD":4,"RED_ARMOR":0,"REGEN":1,"SCOUT":0,"TELEPORTER":0,"YELLOW_ARMOR":18},"PLAY_TIME":1347,"QUIT":0,"RANK":1,"RED_FLAG_PICKUPS":11,"SCORE":615,"STEAM_ID":"76561198194472934","TEAM":2,"TEAM_JOIN_TIME":0,"TEAM_RANK":1,"TIED_RANK":0,"TIED_TEAM_RANK":0,"WARMUP":false,"WEAPONS":{"BFG":{"D":0,"DG":0,"DR":0,"H":0,"K":0,"P":0,"S":0,"T":0},"CHAINGUN":{"D":0,"DG":0,"DR":0,"H":0,"K":0,"P":0,"S":0,"T":0},"GAUNTLET":{"D":0,"DG":50,"DR":0,"H":0,"K":0,"P":0,"S":0,"T":23},"GRENADE":{"D":0,"DG":329,"DR":0,"H":7,"K":1,"P":11,"S":65,"T":66},"HMG":{"D":0,"DG":0,"DR":0,"H":0,"K":0,"P":0,"S":0,"T":0},"LIGHTNING":{"D":0,"DG":0,"DR":0,"H":0,"K":0,"P":0,"S":0,"T":0},"MACHINEGUN":{"D":2,"DG":460,"DR":484,"H":92,"K":2,"P":0,"S":236,"T":483},"NAILGUN":{"D":0,"DG":0,"DR":0,"H":0,"K":0,"P":0,"S":0,"T":0},"OTHER_WEAPON":{"D":0,"DG":0,"DR":0,"H":0,"K":0,"P":0,"S":0,"T":0},"PLASMA":{"D":1,"DG":1963,"DR":280,"H":90,"K":12,"P":31,"S":575,"T":152},"PROXMINE":{"D":0,"DG":0,"DR":0,"H":0,"K":0,"P":0,"S":0,"T":0},"RAILGUN":{"D":17,"DG":2560,"DR":2849,"H":22,"K":14,"P":22,"S":34,"T":126},"ROCKET":{"D":17,"DG":2933,"DR":2683,"H":61,"K":14,"P":42,"S":147,"T":368},"SHOTGUN":{"D":16,"DG":2040,"DR":2006,"H":378,"K":13,"P":29,"S":1240,"T":126}},"WIN":1},{"ABORTED":false,"BLUE_FLAG_PICKUPS":8,"DAMAGE":{"DEALT":10916,"TAKEN":6780},"DEATHS":47,"HOLY_SHITS":0,"ITEM_TIMING":{"YELLOW_ARMOR":6613},"KILLS":53,"LOSE":1,"MATCH_GUID":"5aa8f62c-2b1a-4e54-8d9a-fdc1c061ed3d","MAX_STREAK":6,"MEDALS":{"ACCURACY":0,"ASSISTS":0,"CAPTURES":2,"COMBOKILL":0,"DEFENDS":6,"EXCELLENT":2,"FIRSTFRAG":0,"HEADSHOT":0,"HUMILIATION":0,"IMPRESSIVE":10,"MIDAIR":1,"PERFECT":0,"PERFORATED":0,"QUADGOD":0,"RAMPAGE":0,"REVENGE":3},"MODEL":"xaero","NAME":"Karanimo","NEUTRAL_FLAG_PICKUPS":0,"PICKUPS":{"AMMO":20,"ARMOR":38,"ARMOR_REGEN":0,"BATTLESUIT":0,"DOUBLER":0,"FLIGHT":0,"GREEN_ARMOR":0,"GUARD":0,"HASTE":0,"HEALTH":61,"INVIS":0,"INVULNERABILITY":0,"KAMIKAZE":0,"MEDKIT":0,"MEGA_HEALTH":0,"OTHER_HOLDABLE":0,"OTHER_POWERUP":0,"PORTAL":0,"QUAD":5,"RED_ARMOR":0,"REGEN":4,"SCOUT":0,"TELEPORTER":0,"YELLOW_ARMOR":15},"PLAY_TIME":1347,"QUIT":0,"RANK":2,"RED_FLAG_PICKUPS":0,"SCORE":516,"STEAM_ID":"76561198019911533","TEAM":1,"TEAM_JOIN_TIME":0,"TEAM_RANK":1,"TIED_RANK":0,"TIED_TEAM_RANK":0,"WARMUP":false,"WEAPONS":{"BFG":{"D":0,"DG":0,"DR":0,"H":0,"K":0,"P":0,"S":0,"T":0},"CHAINGUN":{"D":0,"DG":0,"DR":0,"H":0,"K":0,"P":0,"S":0,"T":0},"GAUNTLET":{"D":0,"DG":0,"DR":0,"H":0,"K":0,"P":0,"S":0,"T":0},"GRENADE":{"D":0,"DG":0,"DR":105,"H":0,"K":0,"P":7,"S":4,"T":5},"HMG":{"D":0,"DG":0,"DR":0,"H":0,"K":0,"P":0,"S":0,"T":0},"LIGHTNING":{"D":0,"DG":0,"DR":0,"H":0,"K":0,"P":0,"S":0,"T":0},"MACHINEGUN":{"D":1,"DG":505,"DR":394,"H":101,"K":2,"P":0,"S":338,"T":420},"NAILGUN":{"D":0,"DG":0,"DR":0,"H":0,"K":0,"P":0,"S":0,"T":0},"OTHER_WEAPON":{"D":0,"DG":0,"DR":0,"H":0,"K":0,"P":0,"S":0,"T":0},"PLASMA":{"D":1,"DG":240,"DR":235,"H":14,"K":1,"P":16,"S":75,"T":42},"PROXMINE":{"D":0,"DG":0,"DR":0,"H":0,"K":0,"P":0,"S":0,"T":0},"RAILGUN":{"D":13,"DG":3520,"DR":2304,"H":40,"K":11,"P":33,"S":88,"T":269},"ROCKET":{"D":15,"DG":5331,"DR":1765,"H":91,"K":27,"P":46,"S":183,"T":432},"SHOTGUN":{"D":17,"DG":1320,"DR":1727,"H":248,"K":12,"P":36,"S":800,"T":176}},"WIN":0},{"ABORTED":false,"BLUE_FLAG_PICKUPS":0,"DAMAGE":{"DEALT":6952,"TAKEN":7411},"DEATHS":45,"HOLY_SHITS":0,"ITEM_TIMING":{"YELLOW_ARMOR":4525},"KILLS":33,"LOSE":1,"MATCH_GUID":"5aa8f62c-2b1a-4e54-8d9a-fdc1c061ed3d","MAX_STREAK":6,"MEDALS":{"ACCURACY":0,"ASSISTS":1,"CAPTURES":0,"COMBOKILL":1,"DEFENDS":15,"EXCELLENT":2,"FIRSTFRAG":0,"HEADSHOT":0,"HUMILIATION":0,"IMPRESSIVE":11,"MIDAIR":0,"PERFECT":0,"PERFORATED":0,"QUADGOD":0,"RAMPAGE":0,"REVENGE":4},"MODEL":"sarge","NAME":"Fant1","NEUTRAL_FLAG_PICKUPS":0,"PICKUPS":{"AMMO":23,"ARMOR":96,"ARMOR_REGEN":0,"BATTLESUIT":0,"DOUBLER":0,"FLIGHT":0,"GREEN_ARMOR":0,"GUARD":0,"HASTE":0,"HEALTH":60,"INVIS":0,"INVULNERABILITY":0,"KAMIKAZE":0,"MEDKIT":0,"MEGA_HEALTH":0,"OTHER_HOLDABLE":0,"OTHER_POWERUP":0,"PORTAL":0,"QUAD":1,"RED_ARMOR":0,"REGEN":0,"SCOUT":0,"TELEPORTER":0,"YELLOW_ARMOR":22},"PLAY_TIME":1343,"QUIT":0,"RANK":3,"RED_FLAG_PICKUPS":0,"SCORE":493,"STEAM_ID":"76561198004643746","TEAM":1,"TEAM_JOIN_TIME":0,"TEAM_RANK":2,"TIED_RANK":0,"TIED_TEAM_RANK":0,"WARMUP":false,"WEAPONS":{"BFG":{"D":0,"DG":0,"DR":0,"H":0,"K":0,"P":0,"S":0,"T":0},"CHAINGUN":{"D":0,"DG":0,"DR":0,"H":0,"K":0,"P":0,"S":0,"T":0},"GAUNTLET":{"D":0,"DG":0,"DR":0,"H":0,"K":0,"P":0,"S":0,"T":7},"GRENADE":{"D":1,"DG":0,"DR":208,"H":0,"K":0,"P":10,"S":29,"T":44},"HMG":{"D":0,"DG":0,"DR":0,"H":0,"K":0,"P":0,"S":0,"T":0},"LIGHTNING":{"D":0,"DG":0,"DR":0,"H":0,"K":0,"P":0,"S":0,"T":0},"MACHINEGUN":{"D":1,"DG":480,"DR":571,"H":96,"K":0,"P":0,"S":300,"T":403},"NAILGUN":{"D":0,"DG":0,"DR":0,"H":0,"K":0,"P":0,"S":0,"T":0},"OTHER_WEAPON":{"D":0,"DG":0,"DR":0,"H":0,"K":0,"P":0,"S":0,"T":0},"PLASMA":{"D":4,"DG":140,"DR":625,"H":9,"K":0,"P":8,"S":51,"T":13},"PROXMINE":{"D":0,"DG":0,"DR":0,"H":0,"K":0,"P":0,"S":0,"T":0},"RAILGUN":{"D":13,"DG":2800,"DR":1835,"H":34,"K":15,"P":20,"S":66,"T":232},"ROCKET":{"D":13,"DG":2357,"DR":2228,"H":53,"K":12,"P":38,"S":143,"T":451},"SHOTGUN":{"D":13,"DG":1175,"DR":1744,"H":239,"K":6,"P":38,"S":900,"T":190}},"WIN":0},{"ABORTED":false,"BLUE_FLAG_PICKUPS":0,"DAMAGE":{"DEALT":11924,"TAKEN":8163},"DEATHS":57,"HOLY_SHITS":0,"ITEM_TIMING":{"YELLOW_ARMOR":4203},"KILLS":68,"LOSE":0,"MATCH_GUID":"5aa8f62c-2b1a-4e54-8d9a-fdc1c061ed3d","MAX_STREAK":7,"MEDALS":{"ACCURACY":0,"ASSISTS":1,"CAPTURES":0,"COMBOKILL":0,"DEFENDS":16,"EXCELLENT":6,"FIRSTFRAG":0,"HEADSHOT":1,"HUMILIATION":0,"IMPRESSIVE":19,"MIDAIR":1,"PERFECT":0,"PERFORATED":0,"QUADGOD":0,"RAMPAGE":0,"REVENGE":6},"MODEL":"bitterman","NAME":"Spike Spiegel","NEUTRAL_FLAG_PICKUPS":0,"PICKUPS":{"AMMO":13,"ARMOR":17,"ARMOR_REGEN":0,"BATTLESUIT":0,"DOUBLER":0,"FLIGHT":0,"GREEN_ARMOR":0,"GUARD":0,"HASTE":0,"HEALTH":41,"INVIS":0,"INVULNERABILITY":0,"KAMIKAZE":0,"MEDKIT":0,"MEGA_HEALTH":0,"OTHER_HOLDABLE":0,"OTHER_POWERUP":0,"PORTAL":0,"QUAD":5,"RED_ARMOR":0,"REGEN":2,"SCOUT":0,"TELEPORTER":0,"YELLOW_ARMOR":13},"PLAY_TIME":1198,"QUIT":0,"RANK":4,"RED_FLAG_PICKUPS":2,"SCORE":458,"STEAM_ID":"76561198002376252","TEAM":2,"TEAM_JOIN_TIME":1,"TEAM_RANK":2,"TIED_RANK":0,"TIED_TEAM_RANK":0,"WARMUP":false,"WEAPONS":{"BFG":{"D":0,"DG":0,"DR":0,"H":0,"K":0,"P":0,"S":0,"T":0},"CHAINGUN":{"D":0,"DG":0,"DR":0,"H":0,"K":0,"P":0,"S":0,"T":0},"GAUNTLET":{"D":0,"DG":0,"DR":0,"H":0,"K":0,"P":0,"S":0,"T":3},"GRENADE":{"D":0,"DG":131,"DR":0,"H":3,"K":0,"P":15,"S":8,"T":10},"HMG":{"D":0,"DG":0,"DR":0,"H":0,"K":0,"P":0,"S":0,"T":0},"LIGHTNING":{"D":0,"DG":0,"DR":0,"H":0,"K":0,"P":0,"S":0,"T":0},"MACHINEGUN":{"D":3,"DG":720,"DR":490,"H":146,"K":2,"P":0,"S":383,"T":329},"NAILGUN":{"D":0,"DG":0,"DR":0,"H":0,"K":0,"P":0,"S":0,"T":0},"OTHER_WEAPON":{"D":0,"DG":0,"DR":0,"H":0,"K":0,"P":0,"S":0,"T":0},"PLASMA":{"D":1,"DG":60,"DR":138,"H":3,"K":1,"P":9,"S":11,"T":2},"PROXMINE":{"D":0,"DG":0,"DR":0,"H":0,"K":0,"P":0,"S":0,"T":0},"RAILGUN":{"D":11,"DG":6080,"DR":2324,"H":57,"K":30,"P":34,"S":93,"T":281},"ROCKET":{"D":20,"DG":3058,"DR":2599,"H":70,"K":16,"P":50,"S":141,"T":375},"SHOTGUN":{"D":22,"DG":1875,"DR":2497,"H":343,"K":19,"P":42,"S":1280,"T":193}},"WIN":1},{"ABORTED":false,"BLUE_FLAG_PICKUPS":0,"DAMAGE":{"DEALT":4225,"TAKEN":6540},"DEATHS":35,"HOLY_SHITS":0,"ITEM_TIMING":{"YELLOW_ARMOR":2186},"KILLS":28,"LOSE":0,"MATCH_GUID":"5aa8f62c-2b1a-4e54-8d9a-fdc1c061ed3d","MAX_STREAK":9,"MEDALS":{"ACCURACY":0,"ASSISTS":1,"CAPTURES":0,"COMBOKILL":0,"DEFENDS":12,"EXCELLENT":0,"FIRSTFRAG":0,"HEADSHOT":0,"HUMILIATION":0,"IMPRESSIVE":1,"MIDAIR":1,"PERFECT":0,"PERFORATED":0,"QUADGOD":0,"RAMPAGE":0,"REVENGE":4},"MODEL":"razor/id","NAME":"Solmyr","NEUTRAL_FLAG_PICKUPS":0,"PICKUPS":{"AMMO":26,"ARMOR":102,"ARMOR_REGEN":0,"BATTLESUIT":0,"DOUBLER":0,"FLIGHT":0,"GREEN_ARMOR":0,"GUARD":0,"HASTE":0,"HEALTH":61,"INVIS":0,"INVULNERABILITY":0,"KAMIKAZE":0,"MEDKIT":0,"MEGA_HEALTH":0,"OTHER_HOLDABLE":0,"OTHER_POWERUP":0,"PORTAL":0,"QUAD":1,"RED_ARMOR":0,"REGEN":1,"SCOUT":0,"TELEPORTER":0,"YELLOW_ARMOR":27},"PLAY_TIME":1347,"QUIT":0,"RANK":5,"RED_FLAG_PICKUPS":0,"SCORE":439,"STEAM_ID":"76561198072693862","TEAM":2,"TEAM_JOIN_TIME":0,"TEAM_RANK":3,"TIED_RANK":0,"TIED_TEAM_RANK":0,"WARMUP":false,"WEAPONS":{"BFG":{"D":0,"DG":0,"DR":0,"H":0,"K":0,"P":0,"S":0,"T":0},"CHAINGUN":{"D":0,"DG":0,"DR":0,"H":0,"K":0,"P":0,"S":0,"T":0},"GAUNTLET":{"D":0,"DG":0,"DR":0,"H":0,"K":0,"P":0,"S":0,"T":0},"GRENADE":{"D":0,"DG":0,"DR":0,"H":0,"K":0,"P":10,"S":2,"T":2},"HMG":{"D":0,"DG":0,"DR":0,"H":0,"K":0,"P":0,"S":0,"T":0},"LIGHTNING":{"D":0,"DG":0,"DR":0,"H":0,"K":0,"P":0,"S":0,"T":0},"MACHINEGUN":{"D":3,"DG":135,"DR":249,"H":27,"K":4,"P":0,"S":170,"T":353},"NAILGUN":{"D":0,"DG":0,"DR":0,"H":0,"K":0,"P":0,"S":0,"T":0},"OTHER_WEAPON":{"D":0,"DG":0,"DR":0,"H":0,"K":0,"P":0,"S":0,"T":0},"PLASMA":{"D":0,"DG":20,"DR":0,"H":1,"K":1,"P":3,"S":10,"T":14},"PROXMINE":{"D":0,"DG":0,"DR":0,"H":0,"K":0,"P":0,"S":0,"T":0},"RAILGUN":{"D":9,"DG":400,"DR":1610,"H":5,"K":4,"P":17,"S":39,"T":148},"ROCKET":{"D":14,"DG":1740,"DR":3446,"H":39,"K":10,"P":34,"S":144,"T":440},"SHOTGUN":{"D":9,"DG":1930,"DR":1135,"H":397,"K":9,"P":59,"S":1680,"T":389}},"WIN":1},{"ABORTED":false,"BLUE_FLAG_PICKUPS":3,"DAMAGE":{"DEALT":8020,"TAKEN":6861},"DEATHS":45,"HOLY_SHITS":0,"ITEM_TIMING":{"YELLOW_ARMOR":2876},"KILLS":51,"LOSE":1,"MATCH_GUID":"5aa8f62c-2b1a-4e54-8d9a-fdc1c061ed3d","MAX_STREAK":4,"MEDALS":{"ACCURACY":0,"ASSISTS":1,"CAPTURES":1,"COMBOKILL":0,"DEFENDS":14,"EXCELLENT":3,"FIRSTFRAG":0,"HEADSHOT":1,"HUMILIATION":0,"IMPRESSIVE":5,"MIDAIR":0,"PERFECT":0,"PERFORATED":0,"QUADGOD":0,"RAMPAGE":0,"REVENGE":4},"MODEL":"mynx/bright","NAME":"^1R^7iri^1W^7oo","NEUTRAL_FLAG_PICKUPS":0,"PICKUPS":{"AMMO":15,"ARMOR":24,"ARMOR_REGEN":0,"BATTLESUIT":0,"DOUBLER":0,"FLIGHT":0,"GREEN_ARMOR":0,"GUARD":0,"HASTE":0,"HEALTH":57,"INVIS":0,"INVULNERABILITY":0,"KAMIKAZE":0,"MEDKIT":0,"MEGA_HEALTH":0,"OTHER_HOLDABLE":0,"OTHER_POWERUP":0,"PORTAL":0,"QUAD":3,"RED_ARMOR":0,"REGEN":2,"SCOUT":0,"TELEPORTER":0,"YELLOW_ARMOR":14},"PLAY_TIME":1347,"QUIT":0,"RANK":6,"RED_FLAG_PICKUPS":0,"SCORE":422,"STEAM_ID":"76561198257496197","TEAM":1,"TEAM_JOIN_TIME":0,"TEAM_RANK":3,"TIED_RANK":0,"TIED_TEAM_RANK":0,"WARMUP":false,"WEAPONS":{"BFG":{"D":0,"DG":0,"DR":0,"H":0,"K":0,"P":0,"S":0,"T":0},"CHAINGUN":{"D":0,"DG":0,"DR":0,"H":0,"K":0,"P":0,"S":0,"T":0},"GAUNTLET":{"D":0,"DG":0,"DR":50,"H":0,"K":0,"P":0,"S":0,"T":0},"GRENADE":{"D":0,"DG":200,"DR":193,"H":2,"K":1,"P":20,"S":21,"T":34},"HMG":{"D":0,"DG":0,"DR":0,"H":0,"K":0,"P":0,"S":0,"T":0},"LIGHTNING":{"D":0,"DG":0,"DR":0,"H":0,"K":0,"P":0,"S":0,"T":0},"MACHINEGUN":{"D":4,"DG":265,"DR":563,"H":53,"K":1,"P":0,"S":257,"T":415},"NAILGUN":{"D":0,"DG":0,"DR":0,"H":0,"K":0,"P":0,"S":0,"T":0},"OTHER_WEAPON":{"D":0,"DG":0,"DR":0,"H":0,"K":0,"P":0,"S":0,"T":0},"PLASMA":{"D":3,"DG":0,"DR":266,"H":0,"K":0,"P":6,"S":0,"T":0},"PROXMINE":{"D":0,"DG":0,"DR":0,"H":0,"K":0,"P":0,"S":0,"T":0},"RAILGUN":{"D":14,"DG":1840,"DR":1637,"H":23,"K":11,"P":34,"S":54,"T":190},"ROCKET":{"D":16,"DG":2665,"DR":2512,"H":56,"K":12,"P":41,"S":148,"T":431},"SHOTGUN":{"D":8,"DG":3050,"DR":1455,"H":588,"K":26,"P":53,"S":2260,"T":275}},"WIN":0},{"ABORTED":false,"BLUE_FLAG_PICKUPS":0,"DAMAGE":{"DEALT":5798,"TAKEN":7418},"DEATHS":52,"HOLY_SHITS":0,"ITEM_TIMING":{"YELLOW_ARMOR":4220},"KILLS":23,"LOSE":0,"MATCH_GUID":"5aa8f62c-2b1a-4e54-8d9a-fdc1c061ed3d","MAX_STREAK":5,"MEDALS":{"ACCURACY":0,"ASSISTS":1,"CAPTURES":1,"COMBOKILL":0,"DEFENDS":9,"EXCELLENT":0,"FIRSTFRAG":0,"HEADSHOT":0,"HUMILIATION":0,"IMPRESSIVE":2,"MIDAIR":0,"PERFECT":0,"PERFORATED":0,"QUADGOD":0,"RAMPAGE":0,"REVENGE":9},"MODEL":"anarki","NAME":"mikhronaut","NEUTRAL_FLAG_PICKUPS":0,"PICKUPS":{"AMMO":22,"ARMOR":38,"ARMOR_REGEN":0,"BATTLESUIT":0,"DOUBLER":0,"FLIGHT":0,"GREEN_ARMOR":0,"GUARD":0,"HASTE":0,"HEALTH":58,"INVIS":0,"INVULNERABILITY":0,"KAMIKAZE":0,"MEDKIT":0,"MEGA_HEALTH":0,"OTHER_HOLDABLE":0,"OTHER_POWERUP":0,"PORTAL":0,"QUAD":2,"RED_ARMOR":0,"REGEN":2,"SCOUT":0,"TELEPORTER":0,"YELLOW_ARMOR":12},"PLAY_TIME":1347,"QUIT":0,"RANK":7,"RED_FLAG_PICKUPS":7,"SCORE":382,"STEAM_ID":"76561198121964872","TEAM":2,"TEAM_JOIN_TIME":0,"TEAM_RANK":4,"TIED_RANK":0,"TIED_TEAM_RANK":0,"WARMUP":false,"WEAPONS":{"BFG":{"D":0,"DG":0,"DR":0,"H":0,"K":0,"P":0,"S":0,"T":0},"CHAINGUN":{"D":0,"DG":0,"DR":0,"H":0,"K":0,"P":0,"S":0,"T":0},"GAUNTLET":{"D":0,"DG":0,"DR":0,"H":0,"K":0,"P":0,"S":0,"T":0},"GRENADE":{"D":0,"DG":190,"DR":0,"H":2,"K":0,"P":10,"S":15,"T":36},"HMG":{"D":0,"DG":0,"DR":0,"H":0,"K":0,"P":0,"S":0,"T":0},"LIGHTNING":{"D":0,"DG":0,"DR":0,"H":0,"K":0,"P":0,"S":0,"T":0},"MACHINEGUN":{"D":0,"DG":420,"DR":160,"H":84,"K":1,"P":0,"S":519,"T":443},"NAILGUN":{"D":0,"DG":0,"DR":0,"H":0,"K":0,"P":0,"S":0,"T":0},"OTHER_WEAPON":{"D":0,"DG":0,"DR":0,"H":0,"K":0,"P":0,"S":0,"T":0},"PLASMA":{"D":0,"DG":238,"DR":80,"H":14,"K":0,"P":10,"S":217,"T":67},"PROXMINE":{"D":0,"DG":0,"DR":0,"H":0,"K":0,"P":0,"S":0,"T":0},"RAILGUN":{"D":18,"DG":1040,"DR":2798,"H":13,"K":2,"P":18,"S":31,"T":182},"ROCKET":{"D":24,"DG":2295,"DR":2839,"H":46,"K":13,"P":42,"S":137,"T":410},"SHOTGUN":{"D":10,"DG":1615,"DR":1336,"H":292,"K":7,"P":42,"S":1340,"T":206}},"WIN":1},{"ABORTED":false,"BLUE_FLAG_PICKUPS":0,"DAMAGE":{"DEALT":9563,"TAKEN":6174},"DEATHS":40,"HOLY_SHITS":0,"ITEM_TIMING":{"YELLOW_ARMOR":5853},"KILLS":53,"LOSE":1,"MATCH_GUID":"5aa8f62c-2b1a-4e54-8d9a-fdc1c061ed3d","MAX_STREAK":6,"MEDALS":{"ACCURACY":0,"ASSISTS":0,"CAPTURES":0,"COMBOKILL":1,"DEFENDS":9,"EXCELLENT":2,"FIRSTFRAG":0,"HEADSHOT":0,"HUMILIATION":0,"IMPRESSIVE":13,"MIDAIR":0,"PERFECT":0,"PERFORATED":0,"QUADGOD":0,"RAMPAGE":0,"REVENGE":2},"MODEL":"xaero/sport_red","NAME":"iceh","NEUTRAL_FLAG_PICKUPS":0,"PICKUPS":{"AMMO":48,"ARMOR":17,"ARMOR_REGEN":0,"BATTLESUIT":0,"DOUBLER":0,"FLIGHT":0,"GREEN_ARMOR":0,"GUARD":0,"HASTE":0,"HEALTH":56,"INVIS":0,"INVULNERABILITY":0,"KAMIKAZE":0,"MEDKIT":0,"MEGA_HEALTH":0,"OTHER_HOLDABLE":0,"OTHER_POWERUP":0,"PORTAL":0,"QUAD":3,"RED_ARMOR":0,"REGEN":1,"SCOUT":0,"TELEPORTER":0,"YELLOW_ARMOR":13},"PLAY_TIME":1347,"QUIT":0,"RANK":8,"RED_FLAG_PICKUPS":0,"SCORE":268,"STEAM_ID":"76561197965611091","TEAM":1,"TEAM_JOIN_TIME":0,"TEAM_RANK":4,"TIED_RANK":0,"TIED_TEAM_RANK":0,"WARMUP":false,"WEAPONS":{"BFG":{"D":0,"DG":0,"DR":0,"H":0,"K":0,"P":0,"S":0,"T":0},"CHAINGUN":{"D":0,"DG":0,"DR":0,"H":0,"K":0,"P":0,"S":0,"T":0},"GAUNTLET":{"D":0,"DG":0,"DR":0,"H":0,"K":0,"P":0,"S":0,"T":0},"GRENADE":{"D":0,"DG":0,"DR":100,"H":0,"K":0,"P":10,"S":0,"T":0},"HMG":{"D":0,"DG":0,"DR":0,"H":0,"K":0,"P":0,"S":0,"T":0},"LIGHTNING":{"D":0,"DG":0,"DR":0,"H":0,"K":0,"P":0,"S":0,"T":0},"MACHINEGUN":{"D":2,"DG":455,"DR":462,"H":92,"K":4,"P":0,"S":271,"T":409},"NAILGUN":{"D":0,"DG":0,"DR":0,"H":0,"K":0,"P":0,"S":0,"T":0},"OTHER_WEAPON":{"D":0,"DG":0,"DR":0,"H":0,"K":0,"P":0,"S":0,"T":0},"PLASMA":{"D":3,"DG":0,"DR":225,"H":0,"K":0,"P":9,"S":0,"T":0},"PROXMINE":{"D":0,"DG":0,"DR":0,"H":0,"K":0,"P":0,"S":0,"T":0},"RAILGUN":{"D":12,"DG":4160,"DR":1811,"H":49,"K":20,"P":33,"S":99,"T":367},"ROCKET":{"D":10,"DG":2613,"DR":1704,"H":57,"K":13,"P":59,"S":146,"T":324},"SHOTGUN":{"D":13,"DG":2335,"DR":1802,"H":419,"K":16,"P":40,"S":1860,"T":246}},"WIN":0},{"ABORTED":false,"BLUE_FLAG_PICKUPS":0,"DAMAGE":{"DEALT":8027,"TAKEN":7761},"DEATHS":50,"HOLY_SHITS":0,"ITEM_TIMING":{"YELLOW_ARMOR":3676},"KILLS":42,"LOSE":0,"MATCH_GUID":"5aa8f62c-2b1a-4e54-8d9a-fdc1c061ed3d","MAX_STREAK":6,"MEDALS":{"ACCURACY":0,"ASSISTS":0,"CAPTURES":0,"COMBOKILL":1,"DEFENDS":11,"EXCELLENT":0,"FIRSTFRAG":0,"HEADSHOT":0,"HUMILIATION":0,"IMPRESSIVE":12,"MIDAIR":0,"PERFECT":0,"PERFORATED":0,"QUADGOD":0,"RAMPAGE":0,"REVENGE":4},"MODEL":"ranger","NAME":"^2B^7*^2C ^7ke^21^7e","NEUTRAL_FLAG_PICKUPS":0,"PICKUPS":{"AMMO":17,"ARMOR":16,"ARMOR_REGEN":0,"BATTLESUIT":0,"DOUBLER":0,"FLIGHT":0,"GREEN_ARMOR":0,"GUARD":0,"HASTE":0,"HEALTH":52,"INVIS":0,"INVULNERABILITY":0,"KAMIKAZE":0,"MEDKIT":0,"MEGA_HEALTH":0,"OTHER_HOLDABLE":0,"OTHER_POWERUP":0,"PORTAL":0,"QUAD":3,"RED_ARMOR":0,"REGEN":2,"SCOUT":0,"TELEPORTER":0,"YELLOW_ARMOR":20},"PLAY_TIME":1346,"QUIT":0,"RANK":9,"RED_FLAG_PICKUPS":4,"SCORE":250,"STEAM_ID":"76561198257047592","TEAM":2,"TEAM_JOIN_TIME":0,"TEAM_RANK":5,"TIED_RANK":0,"TIED_TEAM_RANK":0,"WARMUP":false,"WEAPONS":{"BFG":{"D":0,"DG":0,"DR":0,"H":0,"K":0,"P":0,"S":0,"T":0},"CHAINGUN":{"D":0,"DG":0,"DR":0,"H":0,"K":0,"P":0,"S":0,"T":0},"GAUNTLET":{"D":0,"DG":0,"DR":50,"H":0,"K":0,"P":0,"S":0,"T":0},"GRENADE":{"D":2,"DG":0,"DR":251,"H":0,"K":0,"P":10,"S":19,"T":22},"HMG":{"D":0,"DG":0,"DR":0,"H":0,"K":0,"P":0,"S":0,"T":0},"LIGHTNING":{"D":0,"DG":0,"DR":0,"H":0,"K":0,"P":0,"S":0,"T":0},"MACHINEGUN":{"D":2,"DG":590,"DR":728,"H":118,"K":1,"P":0,"S":377,"T":408},"NAILGUN":{"D":0,"DG":0,"DR":0,"H":0,"K":0,"P":0,"S":0,"T":0},"OTHER_WEAPON":{"D":0,"DG":0,"DR":0,"H":0,"K":0,"P":0,"S":0,"T":0},"PLASMA":{"D":0,"DG":60,"DR":-18,"H":3,"K":1,"P":14,"S":10,"T":4},"PROXMINE":{"D":0,"DG":0,"DR":0,"H":0,"K":0,"P":0,"S":0,"T":0},"RAILGUN":{"D":14,"DG":2960,"DR":2319,"H":37,"K":14,"P":24,"S":63,"T":253},"ROCKET":{"D":17,"DG":2202,"DR":2682,"H":56,"K":11,"P":36,"S":145,"T":329},"SHOTGUN":{"D":15,"DG":2215,"DR":1529,"H":425,"K":15,"P":41,"S":2120,"T":328}},"WIN":1},{"ABORTED":false,"BLUE_FLAG_PICKUPS":1,"DAMAGE":{"DEALT":4148,"TAKEN":2867},"DEATHS":21,"HOLY_SHITS":0,"ITEM_TIMING":{"YELLOW_ARMOR":5225},"KILLS":19,"LOSE":1,"MATCH_GUID":"5aa8f62c-2b1a-4e54-8d9a-fdc1c061ed3d","MAX_STREAK":6,"MEDALS":{"ACCURACY":0,"ASSISTS":2,"CAPTURES":0,"COMBOKILL":0,"DEFENDS":1,"EXCELLENT":0,"FIRSTFRAG":0,"HEADSHOT":0,"HUMILIATION":0,"IMPRESSIVE":4,"MIDAIR":0,"PERFECT":0,"PERFORATED":0,"QUADGOD":0,"RAMPAGE":0,"REVENGE":2},"MODEL":"Xaero","NAME":"^4^2BIG^4^7m^2i^1L^7kc^1OW^7","NEUTRAL_FLAG_PICKUPS":0,"PICKUPS":{"AMMO":14,"ARMOR":2,"ARMOR_REGEN":0,"BATTLESUIT":0,"DOUBLER":0,"FLIGHT":0,"GREEN_ARMOR":0,"GUARD":0,"HASTE":0,"HEALTH":23,"INVIS":0,"INVULNERABILITY":0,"KAMIKAZE":0,"MEDKIT":0,"MEGA_HEALTH":0,"OTHER_HOLDABLE":0,"OTHER_POWERUP":0,"PORTAL":0,"QUAD":3,"RED_ARMOR":0,"REGEN":0,"SCOUT":0,"TELEPORTER":0,"YELLOW_ARMOR":3},"PLAY_TIME":436,"QUIT":0,"RANK":10,"RED_FLAG_PICKUPS":0,"SCORE":180,"STEAM_ID":"76561198168171667","TEAM":1,"TEAM_JOIN_TIME":763,"TEAM_RANK":5,"TIED_RANK":0,"TIED_TEAM_RANK":0,"WARMUP":false,"WEAPONS":{"BFG":{"D":0,"DG":0,"DR":0,"H":0,"K":0,"P":0,"S":0,"T":0},"CHAINGUN":{"D":0,"DG":0,"DR":0,"H":0,"K":0,"P":0,"S":0,"T":0},"GAUNTLET":{"D":0,"DG":50,"DR":0,"H":0,"K":0,"P":0,"S":0,"T":13},"GRENADE":{"D":0,"DG":0,"DR":0,"H":0,"K":0,"P":5,"S":0,"T":1},"HMG":{"D":0,"DG":0,"DR":0,"H":0,"K":0,"P":0,"S":0,"T":0},"LIGHTNING":{"D":0,"DG":0,"DR":0,"H":0,"K":0,"P":0,"S":0,"T":0},"MACHINEGUN":{"D":2,"DG":60,"DR":231,"H":12,"K":0,"P":0,"S":94,"T":123},"NAILGUN":{"D":0,"DG":0,"DR":0,"H":0,"K":0,"P":0,"S":0,"T":0},"OTHER_WEAPON":{"D":0,"DG":0,"DR":0,"H":0,"K":0,"P":0,"S":0,"T":0},"PLASMA":{"D":3,"DG":160,"DR":278,"H":8,"K":1,"P":3,"S":26,"T":23},"PROXMINE":{"D":0,"DG":0,"DR":0,"H":0,"K":0,"P":0,"S":0,"T":0},"RAILGUN":{"D":6,"DG":2080,"DR":937,"H":20,"K":10,"P":14,"S":40,"T":121},"ROCKET":{"D":7,"DG":1513,"DR":770,"H":22,"K":6,"P":18,"S":39,"T":100},"SHOTGUN":{"D":3,"DG":285,"DR":571,"H":57,"K":2,"P":16,"S":220,"T":53}},"WIN":0}]}