{"serverIp":"46.101.230.5","serverPort":"27960","gameEndTimestamp":1448653329,"matchStats":{"ABORTED":false,"CAPTURE_LIMIT":8,"EXIT_MSG":"Timelimit hit.","FACTORY":"ctf2","FACTORY_TITLE":"Capture The Flag Timelimit 20","FIRST_SCORER":"Platzpatron","FRAG_LIMIT":50,"GAME_LENGTH":1200,"GAME_TYPE":"CTF","INFECTED":0,"INSTAGIB":0,"LAST_LEAD_CHANGE_TIME":251500,"LAST_SCORER":"att|kubs0n","LAST_TEAMSCORER":"just chillin","MAP":"thedukesgarden","MATCH_GUID":"9eb7195e-0d19-406f-8044-91c1d52d15b4","MERCY_LIMIT":0,"QUADHOG":0,"RESTARTED":0,"SCORE_LIMIT":150,"SERVER_TITLE":"#omega Quakenet CTF DE #1","TIME_LIMIT":20,"TRAINING":0,"TSCORE0":3,"TSCORE1":0},"playerStats":[{"ABORTED":false,"BLUE_FLAG_PICKUPS":8,"DAMAGE":{"DEALT":11766,"TAKEN":7778},"DEATHS":34,"HOLY_SHITS":0,"ITEM_TIMING":{"MEGA_HEALTH":11180,"YELLOW_ARMOR":7576},"KILLS":67,"LOSE":0,"MATCH_GUID":"9eb7195e-0d19-406f-8044-91c1d52d15b4","MAX_STREAK":8,"MEDALS":{"ACCURACY":0,"ASSISTS":1,"CAPTURES":1,"COMBOKILL":0,"DEFENDS":8,"EXCELLENT":10,"FIRSTFRAG":0,"HEADSHOT":0,"HUMILIATION":1,"IMPRESSIVE":12,"MIDAIR":0,"PERFECT":0,"PERFORATED":0,"QUADGOD":0,"RAMPAGE":0,"REVENGE":2},"MODEL":"xaero","NAME":"^4att^3|^7kubs0n","NEUTRAL_FLAG_PICKUPS":0,"PICKUPS":{"AMMO":39,"ARMOR":67,"ARMOR_REGEN":0,"BATTLESUIT":0,"DOUBLER":0,"FLIGHT":0,"GREEN_ARMOR":0,"GUARD":0,"HASTE":0,"HEALTH":43,"INVIS":0,"INVULNERABILITY":0,"KAMIKAZE":0,"MEDKIT":0,"MEGA_HEALTH":5,"OTHER_HOLDABLE":0,"OTHER_POWERUP":0,"PORTAL":0,"QUAD":9,"RED_ARMOR":0,"REGEN":12,"SCOUT":0,"TELEPORTER":0,"YELLOW_ARMOR":32},"PLAY_TIME":1351,"QUIT":0,"RANK":1,"RED_FLAG_PICKUPS":0,"SCORE":439,"STEAM_ID":"76561198245751264","TEAM":1,"TEAM_JOIN_TIME":0,"TEAM_RANK":1,"TIED_RANK":0,"TIED_TEAM_RANK":0,"WARMUP":false,"WEAPONS":{"BFG":{"D":0,"DG":0,"DR":0,"H":0,"K":0,"P":0,"S":0,"T":0},"CHAINGUN":{"D":0,"DG":0,"DR":0,"H":0,"K":0,"P":0,"S":0,"T":0},"GAUNTLET":{"D":0,"DG":100,"DR":0,"H":0,"K":1,"P":0,"S":0,"T":88},"GRENADE":{"D":0,"DG":0,"DR":0,"H":0,"K":0,"P":0,"S":0,"T":0},"HMG":{"D":0,"DG":0,"DR":0,"H":0,"K":0,"P":0,"S":0,"T":0},"LIGHTNING":{"D":3,"DG":3900,"DR":860,"H":431,"K":22,"P":31,"S":1323,"T":139},"MACHINEGUN":{"D":1,"DG":310,"DR":311,"H":62,"K":0,"P":0,"S":189,"T":386},"NAILGUN":{"D":0,"DG":0,"DR":0,"H":0,"K":0,"P":0,"S":0,"T":0},"OTHER_WEAPON":{"D":0,"DG":0,"DR":0,"H":0,"K":0,"P":0,"S":0,"T":0},"PLASMA":{"D":2,"DG":20,"DR":58,"H":1,"K":0,"P":2,"S":4,"T":3},"PROXMINE":{"D":0,"DG":0,"DR":0,"H":0,"K":0,"P":0,"S":0,"T":0},"RAILGUN":{"D":14,"DG":3680,"DR":2972,"H":42,"K":21,"P":28,"S":106,"T":293},"ROCKET":{"D":11,"DG":991,"DR":2429,"H":18,"K":4,"P":24,"S":74,"T":222},"SHOTGUN":{"D":3,"DG":2765,"DR":1098,"H":392,"K":19,"P":34,"S":1580,"T":217}},"WIN":1},{"ABORTED":false,"BLUE_FLAG_PICKUPS":0,"DAMAGE":{"DEALT":3461,"TAKEN":2807},"DEATHS":5,"HOLY_SHITS":0,"ITEM_TIMING":{"MEGA_HEALTH":8409,"YELLOW_ARMOR":8327},"KILLS":22,"LOSE":0,"MATCH_GUID":"9eb7195e-0d19-406f-8044-91c1d52d15b4","MAX_STREAK":9,"MEDALS":{"ACCURACY":0,"ASSISTS":1,"CAPTURES":0,"COMBOKILL":0,"DEFENDS":9,"EXCELLENT":0,"FIRSTFRAG":0,"HEADSHOT":1,"HUMILIATION":0,"IMPRESSIVE":9,"MIDAIR":0,"PERFECT":0,"PERFORATED":0,"QUADGOD":0,"RAMPAGE":0,"REVENGE":0},"MODEL":"mynx/default","NAME":"pa^1nd^7a so^1ph^7ia","NEUTRAL_FLAG_PICKUPS":0,"PICKUPS":{"AMMO":36,"ARMOR":140,"ARMOR_REGEN":0,"BATTLESUIT":0,"DOUBLER":0,"FLIGHT":0,"GREEN_ARMOR":0,"GUARD":0,"HASTE":0,"HEALTH":85,"INVIS":0,"INVULNERABILITY":0,"KAMIKAZE":0,"MEDKIT":0,"MEGA_HEALTH":24,"OTHER_HOLDABLE":0,"OTHER_POWERUP":0,"PORTAL":0,"QUAD":0,"RED_ARMOR":0,"REGEN":0,"SCOUT":0,"TELEPORTER":0,"YELLOW_ARMOR":35},"PLAY_TIME":1351,"QUIT":0,"RANK":2,"RED_FLAG_PICKUPS":0,"SCORE":429,"STEAM_ID":"76561198155662969","TEAM":1,"TEAM_JOIN_TIME":0,"TEAM_RANK":2,"TIED_RANK":0,"TIED_TEAM_RANK":0,"WARMUP":false,"WEAPONS":{"BFG":{"D":0,"DG":0,"DR":0,"H":0,"K":0,"P":0,"S":0,"T":0},"CHAINGUN":{"D":0,"DG":0,"DR":0,"H":0,"K":0,"P":0,"S":0,"T":0},"GAUNTLET":{"D":0,"DG":0,"DR":0,"H":0,"K":0,"P":0,"S":0,"T":0},"GRENADE":{"D":0,"DG":0,"DR":0,"H":0,"K":0,"P":0,"S":0,"T":0},"HMG":{"D":0,"DG":0,"DR":0,"H":0,"K":0,"P":0,"S":0,"T":0},"LIGHTNING":{"D":1,"DG":1410,"DR":767,"H":242,"K":11,"P":9,"S":942,"T":288},"MACHINEGUN":{"D":0,"DG":60,"DR":45,"H":12,"K":1,"P":0,"S":46,"T":199},"NAILGUN":{"D":0,"DG":0,"DR":0,"H":0,"K":0,"P":0,"S":0,"T":0},"OTHER_WEAPON":{"D":0,"DG":0,"DR":0,"H":0,"K":0,"P":0,"S":0,"T":0},"PLASMA":{"D":0,"DG":0,"DR":228,"H":0,"K":0,"P":10,"S":0,"T":9},"PROXMINE":{"D":0,"DG":0,"DR":0,"H":0,"K":0,"P":0,"S":0,"T":0},"RAILGUN":{"D":0,"DG":1920,"DR":560,"H":24,"K":10,"P":6,"S":53,"T":846},"ROCKET":{"D":3,"DG":71,"DR":625,"H":2,"K":0,"P":9,"S":3,"T":8},"SHOTGUN":{"D":1,"DG":0,"DR":572,"H":0,"K":0,"P":16,"S":0,"T":0}},"WIN":1},{"ABORTED":false,"BLUE_FLAG_PICKUPS":0,"DAMAGE":{"DEALT":6816,"TAKEN":4888},"DEATHS":24,"HOLY_SHITS":0,"ITEM_TIMING":{"MEGA_HEALTH":9423,"YELLOW_ARMOR":14123},"KILLS":25,"LOSE":1,"MATCH_GUID":"9eb7195e-0d19-406f-8044-91c1d52d15b4","MAX_STREAK":7,"MEDALS":{"ACCURACY":0,"ASSISTS":0,"CAPTURES":0,"COMBOKILL":0,"DEFENDS":9,"EXCELLENT":0,"FIRSTFRAG":0,"HEADSHOT":1,"HUMILIATION":0,"IMPRESSIVE":12,"MIDAIR":0,"PERFECT":0,"PERFORATED":0,"QUADGOD":0,"RAMPAGE":0,"REVENGE":1},"MODEL":"ranger","NAME":"^2V^7oo^1D^7oo^5_^3_^7","NEUTRAL_FLAG_PICKUPS":0,"PICKUPS":{"AMMO":34,"ARMOR":67,"ARMOR_REGEN":0,"BATTLESUIT":0,"DOUBLER":0,"FLIGHT":0,"GREEN_ARMOR":0,"GUARD":0,"HASTE":0,"HEALTH":39,"INVIS":0,"INVULNERABILITY":0,"KAMIKAZE":0,"MEDKIT":0,"MEGA_HEALTH":16,"OTHER_HOLDABLE":0,"OTHER_POWERUP":0,"PORTAL":0,"QUAD":3,"RED_ARMOR":0,"REGEN":6,"SCOUT":0,"TELEPORTER":0,"YELLOW_ARMOR":20},"PLAY_TIME":1351,"QUIT":0,"RANK":3,"RED_FLAG_PICKUPS":0,"SCORE":415,"STEAM_ID":"76561198117632275","TEAM":2,"TEAM_JOIN_TIME":0,"TEAM_RANK":1,"TIED_RANK":0,"TIED_TEAM_RANK":0,"WARMUP":false,"WEAPONS":{"BFG":{"D":0,"DG":0,"DR":0,"H":0,"K":0,"P":0,"S":0,"T":0},"CHAINGUN":{"D":0,"DG":0,"DR":0,"H":0,"K":0,"P":0,"S":0,"T":0},"GAUNTLET":{"D":0,"DG":0,"DR":0,"H":0,"K":0,"P":0,"S":0,"T":0},"GRENADE":{"D":0,"DG":0,"DR":0,"H":0,"K":0,"P":0,"S":0,"T":0},"HMG":{"D":0,"DG":0,"DR":0,"H":0,"K":0,"P":0,"S":0,"T":0},"LIGHTNING":{"D":5,"DG":558,"DR":1558,"H":93,"K":0,"P":8,"S":371,"T":68},"MACHINEGUN":{"D":1,"DG":295,"DR":61,"H":59,"K":0,"P":0,"S":255,"T":323},"NAILGUN":{"D":0,"DG":0,"DR":0,"H":0,"K":0,"P":0,"S":0,"T":0},"OTHER_WEAPON":{"D":0,"DG":0,"DR":0,"H":0,"K":0,"P":0,"S":0,"T":0},"PLASMA":{"D":0,"DG":0,"DR":0,"H":0,"K":0,"P":11,"S":26,"T":13},"PROXMINE":{"D":0,"DG":0,"DR":0,"H":0,"K":0,"P":0,"S":0,"T":0},"RAILGUN":{"D":11,"DG":3280,"DR":1706,"H":41,"K":15,"P":17,"S":83,"T":386},"ROCKET":{"D":4,"DG":2143,"DR":907,"H":39,"K":6,"P":32,"S":119,"T":470},"SHOTGUN":{"D":3,"DG":540,"DR":656,"H":91,"K":4,"P":20,"S":280,"T":89}},"WIN":0},{"ABORTED":false,"BLUE_FLAG_PICKUPS":7,"DAMAGE":{"DEALT":8108,"TAKEN":8125},"DEATHS":53,"HOLY_SHITS":0,"ITEM_TIMING":{"MEGA_HEALTH":22337,"YELLOW_ARMOR":10243},"KILLS":45,"LOSE":0,"MATCH_GUID":"9eb7195e-0d19-406f-8044-91c1d52d15b4","MAX_STREAK":4,"MEDALS":{"ACCURACY":0,"ASSISTS":1,"CAPTURES":1,"COMBOKILL":0,"DEFENDS":5,"EXCELLENT":4,"FIRSTFRAG":0,"HEADSHOT":0,"HUMILIATION":0,"IMPRESSIVE":7,"MIDAIR":0,"PERFECT":0,"PERFORATED":0,"QUADGOD":0,"RAMPAGE":0,"REVENGE":5},"MODEL":"doom","NAME":"just chillin","NEUTRAL_FLAG_PICKUPS":0,"PICKUPS":{"AMMO":24,"ARMOR":60,"ARMOR_REGEN":0,"BATTLESUIT":0,"DOUBLER":0,"FLIGHT":0,"GREEN_ARMOR":0,"GUARD":0,"HASTE":0,"HEALTH":19,"INVIS":0,"INVULNERABILITY":0,"KAMIKAZE":0,"MEDKIT":0,"MEGA_HEALTH":2,"OTHER_HOLDABLE":0,"OTHER_POWERUP":0,"PORTAL":0,"QUAD":1,"RED_ARMOR":0,"REGEN":9,"SCOUT":0,"TELEPORTER":0,"YELLOW_ARMOR":18},"PLAY_TIME":1351,"QUIT":0,"RANK":4,"RED_FLAG_PICKUPS":0,"SCORE":368,"STEAM_ID":"76561198000806799","TEAM":1,"TEAM_JOIN_TIME":0,"TEAM_RANK":3,"TIED_RANK":0,"TIED_TEAM_RANK":0,"WARMUP":false,"WEAPONS":{"BFG":{"D":0,"DG":0,"DR":0,"H":0,"K":0,"P":0,"S":0,"T":0},"CHAINGUN":{"D":0,"DG":0,"DR":0,"H":0,"K":0,"P":0,"S":0,"T":0},"GAUNTLET":{"D":0,"DG":0,"DR":0,"H":0,"K":0,"P":0,"S":0,"T":10},"GRENADE":{"D":0,"DG":0,"DR":0,"H":0,"K":0,"P":0,"S":0,"T":0},"HMG":{"D":0,"DG":0,"DR":0,"H":0,"K":0,"P":0,"S":0,"T":0},"LIGHTNING":{"D":8,"DG":2928,"DR":1342,"H":504,"K":16,"P":38,"S":1566,"T":253},"MACHINEGUN":{"D":2,"DG":280,"DR":478,"H":59,"K":2,"P":0,"S":244,"T":533},"NAILGUN":{"D":0,"DG":0,"DR":0,"H":0,"K":0,"P":0,"S":0,"T":0},"OTHER_WEAPON":{"D":0,"DG":0,"DR":0,"H":0,"K":0,"P":0,"S":0,"T":0},"PLASMA":{"D":3,"DG":20,"DR":126,"H":2,"K":1,"P":4,"S":11,"T":19},"PROXMINE":{"D":0,"DG":0,"DR":0,"H":0,"K":0,"P":0,"S":0,"T":0},"RAILGUN":{"D":23,"DG":2000,"DR":3518,"H":24,"K":12,"P":20,"S":52,"T":181},"ROCKET":{"D":9,"DG":2040,"DR":1281,"H":42,"K":8,"P":32,"S":80,"T":196},"SHOTGUN":{"D":8,"DG":840,"DR":1340,"H":178,"K":6,"P":35,"S":680,"T":157}},"WIN":1},{"ABORTED":false,"BLUE_FLAG_PICKUPS":6,"DAMAGE":{"DEALT":8310,"TAKEN":6477},"DEATHS":43,"HOLY_SHITS":0,"ITEM_TIMING":{"MEGA_HEALTH":6900,"YELLOW_ARMOR":11183},"KILLS":47,"LOSE":0,"MATCH_GUID":"9eb7195e-0d19-406f-8044-91c1d52d15b4","MAX_STREAK":4,"MEDALS":{"ACCURACY":0,"ASSISTS":0,"CAPTURES":1,"COMBOKILL":0,"DEFENDS":11,"EXCELLENT":2,"FIRSTFRAG":1,"HEADSHOT":0,"HUMILIATION":2,"IMPRESSIVE":3,"MIDAIR":0,"PERFECT":0,"PERFORATED":0,"QUADGOD":0,"RAMPAGE":0,"REVENGE":5},"MODEL":"sarge","NAME":"Platzpatron","NEUTRAL_FLAG_PICKUPS":0,"PICKUPS":{"AMMO":45,"ARMOR":41,"ARMOR_REGEN":0,"BATTLESUIT":0,"DOUBLER":0,"FLIGHT":0,"GREEN_ARMOR":0,"GUARD":0,"HASTE":0,"HEALTH":23,"INVIS":0,"INVULNERABILITY":0,"KAMIKAZE":0,"MEDKIT":0,"MEGA_HEALTH":1,"OTHER_HOLDABLE":0,"OTHER_POWERUP":0,"PORTAL":0,"QUAD":0,"RED_ARMOR":0,"REGEN":4,"SCOUT":0,"TELEPORTER":0,"YELLOW_ARMOR":23},"PLAY_TIME":1351,"QUIT":0,"RANK":5,"RED_FLAG_PICKUPS":0,"SCORE":344,"STEAM_ID":"76561197970601899","TEAM":1,"TEAM_JOIN_TIME":0,"TEAM_RANK":4,"TIED_RANK":0,"TIED_TEAM_RANK":0,"WARMUP":false,"WEAPONS":{"BFG":{"D":0,"DG":0,"DR":0,"H":0,"K":0,"P":0,"S":0,"T":0},"CHAINGUN":{"D":0,"DG":0,"DR":0,"H":0,"K":0,"P":0,"S":0,"T":0},"GAUNTLET":{"D":1,"DG":200,"DR":220,"H":0,"K":2,"P":0,"S":0,"T":20},"GRENADE":{"D":0,"DG":0,"DR":0,"H":0,"K":0,"P":0,"S":0,"T":0},"HMG":{"D":0,"DG":0,"DR":0,"H":0,"K":0,"P":0,"S":0,"T":0},"LIGHTNING":{"D":10,"DG":1380,"DR":1197,"H":231,"K":7,"P":27,"S":805,"T":147},"MACHINEGUN":{"D":0,"DG":320,"DR":590,"H":64,"K":1,"P":0,"S":288,"T":427},"NAILGUN":{"D":0,"DG":0,"DR":0,"H":0,"K":0,"P":0,"S":0,"T":0},"OTHER_WEAPON":{"D":0,"DG":0,"DR":0,"H":0,"K":0,"P":0,"S":0,"T":0},"PLASMA":{"D":2,"DG":0,"DR":368,"H":0,"K":0,"P":3,"S":0,"T":0},"PROXMINE":{"D":0,"DG":0,"DR":0,"H":0,"K":0,"P":0,"S":0,"T":0},"RAILGUN":{"D":20,"DG":960,"DR":2118,"H":12,"K":5,"P":32,"S":26,"T":144},"ROCKET":{"D":5,"DG":3425,"DR":978,"H":57,"K":17,"P":30,"S":121,"T":399},"SHOTGUN":{"D":5,"DG":2025,"DR":971,"H":416,"K":15,"P":37,"S":1400,"T":212}},"WIN":1},{"ABORTED":false,"BLUE_FLAG_PICKUPS":0,"DAMAGE":{"DEALT":7756,"TAKEN":8277},"DEATHS":50,"HOLY_SHITS":0,"ITEM_TIMING":{"MEGA_HEALTH":4150,"YELLOW_ARMOR":10693},"KILLS":38,"LOSE":1,"MATCH_GUID":"9eb7195e-0d19-406f-8044-91c1d52d15b4","MAX_STREAK":3,"MEDALS":{"ACCURACY":0,"ASSISTS":0,"CAPTURES":0,"COMBOKILL":0,"DEFENDS":16,"EXCELLENT":4,"FIRSTFRAG":0,"HEADSHOT":1,"HUMILIATION":1,"IMPRESSIVE":11,"MIDAIR":0,"PERFECT":0,"PERFORATED":0,"QUADGOD":0,"RAMPAGE":0,"REVENGE":6},"MODEL":"sarge","NAME":"^2ed^7Rush","NEUTRAL_FLAG_PICKUPS":0,"PICKUPS":{"AMMO":45,"ARMOR":74,"ARMOR_REGEN":0,"BATTLESUIT":0,"DOUBLER":0,"FLIGHT":0,"GREEN_ARMOR":0,"GUARD":0,"HASTE":0,"HEALTH":35,"INVIS":0,"INVULNERABILITY":0,"KAMIKAZE":0,"MEDKIT":0,"MEGA_HEALTH":1,"OTHER_HOLDABLE":0,"OTHER_POWERUP":0,"PORTAL":0,"QUAD":2,"RED_ARMOR":0,"REGEN":12,"SCOUT":0,"TELEPORTER":0,"YELLOW_ARMOR":19},"PLAY_TIME":1351,"QUIT":0,"RANK":6,"RED_FLAG_PICKUPS":8,"SCORE":337,"STEAM_ID":"76561197969762379","TEAM":2,"TEAM_JOIN_TIME":0,"TEAM_RANK":2,"TIED_RANK":0,"TIED_TEAM_RANK":0,"WARMUP":false,"WEAPONS":{"BFG":{"D":0,"DG":0,"DR":0,"H":0,"K":0,"P":0,"S":0,"T":0},"CHAINGUN":{"D":0,"DG":0,"DR":0,"H":0,"K":0,"P":0,"S":0,"T":0},"GAUNTLET":{"D":2,"DG":250,"DR":214,"H":0,"K":1,"P":0,"S":0,"T":27},"GRENADE":{"D":0,"DG":0,"DR":0,"H":0,"K":0,"P":0,"S":0,"T":0},"HMG":{"D":0,"DG":0,"DR":0,"H":0,"K":0,"P":0,"S":0,"T":0},"LIGHTNING":{"D":13,"DG":1284,"DR":2853,"H":199,"K":5,"P":24,"S":844,"T":112},"MACHINEGUN":{"D":4,"DG":315,"DR":440,"H":64,"K":2,"P":0,"S":244,"T":522},"NAILGUN":{"D":0,"DG":0,"DR":0,"H":0,"K":0,"P":0,"S":0,"T":0},"OTHER_WEAPON":{"D":0,"DG":0,"DR":0,"H":0,"K":0,"P":0,"S":0,"T":0},"PLASMA":{"D":0,"DG":271,"DR":0,"H":10,"K":3,"P":13,"S":77,"T":42},"PROXMINE":{"D":0,"DG":0,"DR":0,"H":0,"K":0,"P":0,"S":0,"T":0},"RAILGUN":{"D":12,"DG":2560,"DR":2272,"H":28,"K":11,"P":28,"S":48,"T":185},"ROCKET":{"D":9,"DG":2531,"DR":1331,"H":53,"K":14,"P":38,"S":124,"T":384},"SHOTGUN":{"D":10,"DG":545,"DR":1127,"H":109,"K":2,"P":33,"S":480,"T":77}},"WIN":0},{"ABORTED":false,"BLUE_FLAG_PICKUPS":0,"DAMAGE":{"DEALT":5881,"TAKEN":7148},"DEATHS":51,"HOLY_SHITS":0,"ITEM_TIMING":{"MEGA_HEALTH":7608,"YELLOW_ARMOR":4663},"KILLS":29,"LOSE":1,"MATCH_GUID":"9eb7195e-0d19-406f-8044-91c1d52d15b4","MAX_STREAK":6,"MEDALS":{"ACCURACY":0,"ASSISTS":0,"CAPTURES":0,"COMBOKILL":0,"DEFENDS":9,"EXCELLENT":1,"FIRSTFRAG":0,"HEADSHOT":0,"HUMILIATION":1,"IMPRESSIVE":4,"MIDAIR":1,"PERFECT":0,"PERFORATED":0,"QUADGOD":0,"RAMPAGE":0,"REVENGE":8},"MODEL":"bones","NAME":"fly_","NEUTRAL_FLAG_PICKUPS":0,"PICKUPS":{"AMMO":42,"ARMOR":70,"ARMOR_REGEN":0,"BATTLESUIT":0,"DOUBLER":0,"FLIGHT":0,"GREEN_ARMOR":0,"GUARD":0,"HASTE":0,"HEALTH":21,"INVIS":0,"INVULNERABILITY":0,"KAMIKAZE":0,"MEDKIT":0,"MEGA_HEALTH":3,"OTHER_HOLDABLE":0,"OTHER_POWERUP":0,"PORTAL":0,"QUAD":3,"RED_ARMOR":0,"REGEN":3,"SCOUT":0,"TELEPORTER":0,"YELLOW_ARMOR":13},"PLAY_TIME":1351,"QUIT":0,"RANK":7,"RED_FLAG_PICKUPS":1,"SCORE":267,"STEAM_ID":"76561198068048982","TEAM":2,"TEAM_JOIN_TIME":0,"TEAM_RANK":3,"TIED_RANK":0,"TIED_TEAM_RANK":0,"WARMUP":false,"WEAPONS":{"BFG":{"D":0,"DG":0,"DR":0,"H":0,"K":0,"P":0,"S":0,"T":0},"CHAINGUN":{"D":0,"DG":0,"DR":0,"H":0,"K":0,"P":0,"S":0,"T":0},"GAUNTLET":{"D":0,"DG":50,"DR":0,"H":0,"K":1,"P":0,"S":0,"T":23},"GRENADE":{"D":0,"DG":0,"DR":0,"H":0,"K":0,"P":0,"S":0,"T":0},"HMG":{"D":0,"DG":0,"DR":0,"H":0,"K":0,"P":0,"S":0,"T":0},"LIGHTNING":{"D":19,"DG":378,"DR":2707,"H":64,"K":3,"P":18,"S":410,"T":76},"MACHINEGUN":{"D":0,"DG":105,"DR":160,"H":22,"K":0,"P":0,"S":211,"T":442},"NAILGUN":{"D":0,"DG":0,"DR":0,"H":0,"K":0,"P":0,"S":0,"T":0},"OTHER_WEAPON":{"D":0,"DG":0,"DR":0,"H":0,"K":0,"P":0,"S":0,"T":0},"PLASMA":{"D":0,"DG":278,"DR":20,"H":17,"K":3,"P":11,"S":225,"T":67},"PROXMINE":{"D":0,"DG":0,"DR":0,"H":0,"K":0,"P":0,"S":0,"T":0},"RAILGUN":{"D":12,"DG":1520,"DR":1332,"H":18,"K":9,"P":24,"S":61,"T":242},"ROCKET":{"D":8,"DG":2030,"DR":1294,"H":40,"K":8,"P":28,"S":84,"T":246},"SHOTGUN":{"D":11,"DG":1520,"DR":1619,"H":290,"K":5,"P":42,"S":1320,"T":252}},"WIN":0},{"ABORTED":false,"BLUE_FLAG_PICKUPS":0,"DAMAGE":{"DEALT":4908,"TAKEN":7579},"DEATHS":57,"HOLY_SHITS":0,"ITEM_TIMING":{"YELLOW_ARMOR":11382},"KILLS":24,"LOSE":1,"MATCH_GUID":"9eb7195e-0d19-406f-8044-91c1d52d15b4","MAX_STREAK":3,"MEDALS":{"ACCURACY":0,"ASSISTS":0,"CAPTURES":0,"COMBOKILL":0,"DEFENDS":8,"EXCELLENT":0,"FIRSTFRAG":0,"HEADSHOT":1,"HUMILIATION":0,"IMPRESSIVE":7,"MIDAIR":0,"PERFECT":0,"PERFORATED":0,"QUADGOD":0,"RAMPAGE":0,"REVENGE":7},"MODEL":"sarge/default","NAME":"sarge","NEUTRAL_FLAG_PICKUPS":0,"PICKUPS":{"AMMO":32,"ARMOR":5,"ARMOR_REGEN":0,"BATTLESUIT":0,"DOUBLER":0,"FLIGHT":0,"GREEN_ARMOR":0,"GUARD":0,"HASTE":0,"HEALTH":18,"INVIS":0,"INVULNERABILITY":0,"KAMIKAZE":0,"MEDKIT":0,"MEGA_HEALTH":0,"OTHER_HOLDABLE":0,"OTHER_POWERUP":0,"PORTAL":0,"QUAD":0,"RED_ARMOR":0,"REGEN":0,"SCOUT":0,"TELEPORTER":0,"YELLOW_ARMOR":13},"PLAY_TIME":1351,"QUIT":0,"RANK":8,"RED_FLAG_PICKUPS":1,"SCORE":254,"STEAM_ID":"76561198077156894","TEAM":2,"TEAM_JOIN_TIME":0,"TEAM_RANK":4,"TIED_RANK":0,"TIED_TEAM_RANK":0,"WARMUP":false,"WEAPONS":{"BFG":{"D":0,"DG":0,"DR":0,"H":0,"K":0,"P":0,"S":0,"T":0},"CHAINGUN":{"D":0,"DG":0,"DR":0,"H":0,"K":0,"P":0,"S":0,"T":0},"GAUNTLET":{"D":0,"DG":0,"DR":-7,"H":0,"K":0,"P":0,"S":0,"T":0},"GRENADE":{"D":0,"DG":0,"DR":0,"H":0,"K":0,"P":0,"S":0,"T":0},"HMG":{"D":0,"DG":0,"DR":0,"H":0,"K":0,"P":0,"S":0,"T":0},"LIGHTNING":{"D":24,"DG":1146,"DR":2945,"H":197,"K":7,"P":37,"S":1076,"T":218},"MACHINEGUN":{"D":0,"DG":200,"DR":160,"H":40,"K":1,"P":0,"S":277,"T":522},"NAILGUN":{"D":0,"DG":0,"DR":0,"H":0,"K":0,"P":0,"S":0,"T":0},"OTHER_WEAPON":{"D":0,"DG":0,"DR":0,"H":0,"K":0,"P":0,"S":0,"T":0},"PLASMA":{"D":0,"DG":0,"DR":0,"H":0,"K":0,"P":6,"S":56,"T":33},"PROXMINE":{"D":0,"DG":0,"DR":0,"H":0,"K":0,"P":0,"S":0,"T":0},"RAILGUN":{"D":13,"DG":3280,"DR":1751,"H":41,"K":14,"P":38,"S":136,"T":456},"ROCKET":{"D":8,"DG":102,"DR":1425,"H":2,"K":2,"P":16,"S":16,"T":47},"SHOTGUN":{"D":12,"DG":180,"DR":1265,"H":36,"K":0,"P":20,"S":400,"T":73}},"WIN":0},{"ABORTED":false,"BLUE_FLAG_PICKUPS":0,"DAMAGE":{"DEALT":9069,"TAKEN":8106},"DEATHS":53,"HOLY_SHITS":0,"ITEM_TIMING":{"MEGA_HEALTH":16900,"YELLOW_ARMOR":7589},"KILLS":41,"LOSE":1,"MATCH_GUID":"9eb7195e-0d19-406f-8044-91c1d52d15b4","MAX_STREAK":4,"MEDALS":{"ACCURACY":0,"ASSISTS":0,"CAPTURES":0,"COMBOKILL":1,"DEFENDS":12,"EXCELLENT":4,"FIRSTFRAG":0,"HEADSHOT":1,"HUMILIATION":0,"IMPRESSIVE":10,"MIDAIR":0,"PERFECT":0,"PERFORATED":0,"QUADGOD":0,"RAMPAGE":1,"REVENGE":6},"MODEL":"grunt/default","NAME":"smackalodon","NEUTRAL_FLAG_PICKUPS":0,"PICKUPS":{"AMMO":24,"ARMOR":30,"ARMOR_REGEN":0,"BATTLESUIT":0,"DOUBLER":0,"FLIGHT":0,"GREEN_ARMOR":0,"GUARD":0,"HASTE":0,"HEALTH":31,"INVIS":0,"INVULNERABILITY":0,"KAMIKAZE":0,"MEDKIT":0,"MEGA_HEALTH":2,"OTHER_HOLDABLE":0,"OTHER_POWERUP":0,"PORTAL":0,"QUAD":1,"RED_ARMOR":0,"REGEN":5,"SCOUT":0,"TELEPORTER":0,"YELLOW_ARMOR":19},"PLAY_TIME":1351,"QUIT":0,"RANK":9,"RED_FLAG_PICKUPS":3,"SCORE":217,"STEAM_ID":"76561198259839754","TEAM":2,"TEAM_JOIN_TIME":0,"TEAM_RANK":5,"TIED_RANK":0,"TIED_TEAM_RANK":0,"WARMUP":false,"WEAPONS":{"BFG":{"D":0,"DG":0,"DR":0,"H":0,"K":0,"P":0,"S":0,"T":0},"CHAINGUN":{"D":0,"DG":0,"DR":0,"H":0,"K":0,"P":0,"S":0,"T":0},"GAUNTLET":{"D":1,"DG":0,"DR":50,"H":0,"K":0,"P":0,"S":0,"T":1},"GRENADE":{"D":0,"DG":0,"DR":0,"H":0,"K":0,"P":0,"S":0,"T":0},"HMG":{"D":0,"DG":0,"DR":0,"H":0,"K":0,"P":0,"S":0,"T":0},"LIGHTNING":{"D":18,"DG":2316,"DR":3063,"H":392,"K":13,"P":35,"S":936,"T":141},"MACHINEGUN":{"D":2,"DG":850,"DR":293,"H":170,"K":1,"P":0,"S":545,"T":563},"NAILGUN":{"D":0,"DG":0,"DR":0,"H":0,"K":0,"P":0,"S":0,"T":0},"OTHER_WEAPON":{"D":0,"DG":0,"DR":0,"H":0,"K":0,"P":0,"S":0,"T":0},"PLASMA":{"D":1,"DG":320,"DR":-14,"H":20,"K":1,"P":10,"S":126,"T":83},"PROXMINE":{"D":0,"DG":0,"DR":0,"H":0,"K":0,"P":0,"S":0,"T":0},"RAILGUN":{"D":16,"DG":3040,"DR":2364,"H":35,"K":15,"P":22,"S":70,"T":200},"ROCKET":{"D":7,"DG":508,"DR":1341,"H":11,"K":3,"P":15,"S":23,"T":93},"SHOTGUN":{"D":8,"DG":2035,"DR":989,"H":410,"K":8,"P":40,"S":1400,"T":267}},"WIN":0},{"ABORTED":false,"BLUE_FLAG_PICKUPS":3,"DAMAGE":{"DEALT":10105,"TAKEN":5227},"DEATHS":26,"HOLY_SHITS":0,"ITEM_TIMING":{"YELLOW_ARMOR":10196},"KILLS":51,"LOSE":0,"MATCH_GUID":"9eb7195e-0d19-406f-8044-91c1d52d15b4","MAX_STREAK":12,"MEDALS":{"ACCURACY":0,"ASSISTS":0,"CAPTURES":0,"COMBOKILL":1,"DEFENDS":3,"EXCELLENT":1,"FIRSTFRAG":0,"HEADSHOT":0,"HUMILIATION":0,"IMPRESSIVE":16,"MIDAIR":0,"PERFECT":0,"PERFORATED":0,"QUADGOD":0,"RAMPAGE":0,"REVENGE":3},"MODEL":"bitterman","NAME":"Lao","NEUTRAL_FLAG_PICKUPS":0,"PICKUPS":{"AMMO":27,"ARMOR":41,"ARMOR_REGEN":0,"BATTLESUIT":0,"DOUBLER":0,"FLIGHT":0,"GREEN_ARMOR":0,"GUARD":0,"HASTE":0,"HEALTH":32,"INVIS":0,"INVULNERABILITY":0,"KAMIKAZE":0,"MEDKIT":0,"MEGA_HEALTH":0,"OTHER_HOLDABLE":0,"OTHER_POWERUP":0,"PORTAL":0,"QUAD":3,"RED_ARMOR":0,"REGEN":7,"SCOUT":0,"TELEPORTER":0,"YELLOW_ARMOR":15},"PLAY_TIME":1351,"QUIT":0,"RANK":10,"RED_FLAG_PICKUPS":0,"SCORE":200,"STEAM_ID":"76561198171238703","TEAM":1,"TEAM_JOIN_TIME":0,"TEAM_RANK":5,"TIED_RANK":0,"TIED_TEAM_RANK":0,"WARMUP":false,"WEAPONS":{"BFG":{"D":0,"DG":0,"DR":0,"H":0,"K":0,"P":0,"S":0,"T":0},"CHAINGUN":{"D":0,"DG":0,"DR":0,"H":0,"K":0,"P":0,"S":0,"T":0},"GAUNTLET":{"D":1,"DG":0,"DR":40,"H":0,"K":0,"P":0,"S":0,"T":114},"GRENADE":{"D":0,"DG":0,"DR":0,"H":0,"K":0,"P":0,"S":0,"T":0},"HMG":{"D":0,"DG":0,"DR":0,"H":0,"K":0,"P":0,"S":0,"T":0},"LIGHTNING":{"D":6,"DG":4260,"DR":1400,"H":599,"K":23,"P":42,"S":1985,"T":312},"MACHINEGUN":{"D":1,"DG":175,"DR":325,"H":35,"K":3,"P":0,"S":172,"T":305},"NAILGUN":{"D":0,"DG":0,"DR":0,"H":0,"K":0,"P":0,"S":0,"T":0},"OTHER_WEAPON":{"D":0,"DG":0,"DR":0,"H":0,"K":0,"P":0,"S":0,"T":0},"PLASMA":{"D":1,"DG":0,"DR":8,"H":0,"K":0,"P":2,"S":15,"T":3},"PROXMINE":{"D":0,"DG":0,"DR":0,"H":0,"K":0,"P":0,"S":0,"T":0},"RAILGUN":{"D":7,"DG":3840,"DR":1750,"H":45,"K":16,"P":24,"S":77,"T":280},"ROCKET":{"D":8,"DG":1270,"DR":950,"H":19,"K":5,"P":20,"S":54,"T":265},"SHOTGUN":{"D":2,"DG":560,"DR":739,"H":115,"K":4,"P":24,"S":360,"T":69}},"WIN":1}]}