{"serverIp":"188.166.17.6","serverPort":"27960","gameEndTimestamp":1448836982,"matchStats":{"ABORTED":false,"CAPTURE_LIMIT":8,"EXIT_MSG":"Timelimit hit.","FACTORY":"ctf2","FACTORY_TITLE":"Capture The Flag Timelimit 20","FIRST_SCORER":"kanonjon","FRAG_LIMIT":50,"GAME_LENGTH":1200,"GAME_TYPE":"CTF","INFECTED":0,"INSTAGIB":0,"LAST_LEAD_CHANGE_TIME":434675,"LAST_SCORER":"oMg>> Bforce","LAST_TEAMSCORER":"Mr B","MAP":"spidercrossings","MATCH_GUID":"df8ddd67-91da-4ed6-8fe6-9e4b670a9bd2","MERCY_LIMIT":0,"QUADHOG":0,"RESTARTED":0,"SCORE_LIMIT":150,"SERVER_TITLE":"#omega Quakenet CTF NL #1","TIME_LIMIT":20,"TRAINING":0,"TSCORE0":2,"TSCORE1":1},"playerStats":[{"ABORTED":false,"BLUE_FLAG_PICKUPS":0,"DAMAGE":{"DEALT":5931,"TAKEN":4842},"DEATHS":22,"HOLY_SHITS":0,"ITEM_TIMING":{"MEGA_HEALTH":3265,"RED_ARMOR":431,"YELLOW_ARMOR":4860},"KILLS":36,"LOSE":0,"MATCH_GUID":"df8ddd67-91da-4ed6-8fe6-9e4b670a9bd2","MAX_STREAK":11,"MEDALS":{"ACCURACY":0,"ASSISTS":0,"CAPTURES":1,"COMBOKILL":0,"DEFENDS":14,"EXCELLENT":2,"FIRSTFRAG":1,"HEADSHOT":0,"HUMILIATION":0,"IMPRESSIVE":4,"MIDAIR":0,"PERFECT":0,"PERFORATED":0,"QUADGOD":0,"RAMPAGE":0,"REVENGE":1},"MODEL":"ranger/default","NAME":"kanonjon","NEUTRAL_FLAG_PICKUPS":0,"PICKUPS":{"AMMO":55,"ARMOR":0,"ARMOR_REGEN":0,"BATTLESUIT":0,"DOUBLER":0,"FLIGHT":0,"GREEN_ARMOR":0,"GUARD":0,"HASTE":2,"HEALTH":57,"INVIS":0,"INVULNERABILITY":0,"KAMIKAZE":0,"MEDKIT":0,"MEGA_HEALTH":8,"OTHER_HOLDABLE":0,"OTHER_POWERUP":0,"PORTAL":0,"QUAD":1,"RED_ARMOR":4,"REGEN":5,"SCOUT":0,"TELEPORTER":0,"YELLOW_ARMOR":5},"PLAY_TIME":1370,"QUIT":0,"RANK":1,"RED_FLAG_PICKUPS":0,"SCORE":445,"STEAM_ID":"76561198257018686","TEAM":1,"TEAM_JOIN_TIME":0,"TEAM_RANK":1,"TIED_RANK":0,"TIED_TEAM_RANK":0,"WARMUP":false,"WEAPONS":{"BFG":{"D":0,"DG":0,"DR":0,"H":0,"K":0,"P":0,"S":0,"T":0},"CHAINGUN":{"D":0,"DG":0,"DR":0,"H":0,"K":0,"P":0,"S":0,"T":0},"GAUNTLET":{"D":0,"DG":0,"DR":0,"H":0,"K":0,"P":0,"S":0,"T":0},"GRENADE":{"D":0,"DG":0,"DR":0,"H":1,"K":0,"P":13,"S":7,"T":8},"HMG":{"D":0,"DG":0,"DR":0,"H":0,"K":0,"P":0,"S":0,"T":0},"LIGHTNING":{"D":3,"DG":2592,"DR":994,"H":429,"K":19,"P":23,"S":1475,"T":573},"MACHINEGUN":{"D":1,"DG":405,"DR":235,"H":81,"K":2,"P":0,"S":277,"T":348},"NAILGUN":{"D":0,"DG":0,"DR":0,"H":0,"K":0,"P":0,"S":0,"T":0},"OTHER_WEAPON":{"D":0,"DG":0,"DR":0,"H":0,"K":0,"P":0,"S":0,"T":0},"PLASMA":{"D":0,"DG":0,"DR":0,"H":0,"K":0,"P":10,"S":0,"T":0},"PROXMINE":{"D":0,"DG":0,"DR":0,"H":0,"K":0,"P":0,"S":0,"T":0},"RAILGUN":{"D":12,"DG":1200,"DR":1879,"H":15,"K":5,"P":29,"S":28,"T":166},"ROCKET":{"D":5,"DG":1294,"DR":953,"H":28,"K":9,"P":37,"S":105,"T":235},"SHOTGUN":{"D":1,"DG":440,"DR":691,"H":88,"K":1,"P":12,"S":280,"T":37}},"WIN":1},{"ABORTED":false,"BLUE_FLAG_PICKUPS":0,"DAMAGE":{"DEALT":8932,"TAKEN":4687},"DEATHS":30,"HOLY_SHITS":0,"ITEM_TIMING":{"YELLOW_ARMOR":5039},"KILLS":53,"LOSE":0,"MATCH_GUID":"df8ddd67-91da-4ed6-8fe6-9e4b670a9bd2","MAX_STREAK":7,"MEDALS":{"ACCURACY":0,"ASSISTS":0,"CAPTURES":0,"COMBOKILL":0,"DEFENDS":16,"EXCELLENT":5,"FIRSTFRAG":0,"HEADSHOT":2,"HUMILIATION":0,"IMPRESSIVE":24,"MIDAIR":0,"PERFECT":0,"PERFORATED":0,"QUADGOD":0,"RAMPAGE":0,"REVENGE":2},"MODEL":"uriel/zael","NAME":"^5הєτƁǻה^7","NEUTRAL_FLAG_PICKUPS":0,"PICKUPS":{"AMMO":13,"ARMOR":11,"ARMOR_REGEN":0,"BATTLESUIT":0,"DOUBLER":0,"FLIGHT":0,"GREEN_ARMOR":0,"GUARD":0,"HASTE":1,"HEALTH":45,"INVIS":0,"INVULNERABILITY":0,"KAMIKAZE":0,"MEDKIT":0,"MEGA_HEALTH":0,"OTHER_HOLDABLE":0,"OTHER_POWERUP":0,"PORTAL":0,"QUAD":0,"RED_ARMOR":0,"REGEN":2,"SCOUT":0,"TELEPORTER":0,"YELLOW_ARMOR":7},"PLAY_TIME":1370,"QUIT":0,"RANK":2,"RED_FLAG_PICKUPS":0,"SCORE":369,"STEAM_ID":"76561198042075825","TEAM":1,"TEAM_JOIN_TIME":0,"TEAM_RANK":2,"TIED_RANK":0,"TIED_TEAM_RANK":0,"WARMUP":false,"WEAPONS":{"BFG":{"D":0,"DG":0,"DR":0,"H":0,"K":0,"P":0,"S":0,"T":0},"CHAINGUN":{"D":0,"DG":0,"DR":0,"H":0,"K":0,"P":0,"S":0,"T":0},"GAUNTLET":{"D":0,"DG":0,"DR":0,"H":0,"K":0,"P":0,"S":0,"T":0},"GRENADE":{"D":0,"DG":0,"DR":33,"H":0,"K":0,"P":13,"S":19,"T":29},"HMG":{"D":0,"DG":0,"DR":0,"H":0,"K":0,"P":0,"S":0,"T":0},"LIGHTNING":{"D":4,"DG":294,"DR":608,"H":50,"K":3,"P":16,"S":154,"T":101},"MACHINEGUN":{"D":1,"DG":470,"DR":369,"H":95,"K":4,"P":0,"S":334,"T":368},"NAILGUN":{"D":0,"DG":0,"DR":0,"H":0,"K":0,"P":0,"S":0,"T":0},"OTHER_WEAPON":{"D":0,"DG":0,"DR":0,"H":0,"K":0,"P":0,"S":0,"T":0},"PLASMA":{"D":0,"DG":0,"DR":0,"H":0,"K":0,"P":9,"S":0,"T":0},"PROXMINE":{"D":0,"DG":0,"DR":0,"H":0,"K":0,"P":0,"S":0,"T":0},"RAILGUN":{"D":14,"DG":6480,"DR":2250,"H":81,"K":36,"P":50,"S":154,"T":567},"ROCKET":{"D":5,"DG":1063,"DR":999,"H":23,"K":4,"P":35,"S":80,"T":216},"SHOTGUN":{"D":6,"DG":625,"DR":353,"H":135,"K":6,"P":19,"S":460,"T":87}},"WIN":1},{"ABORTED":false,"BLUE_FLAG_PICKUPS":0,"DAMAGE":{"DEALT":9643,"TAKEN":5889},"DEATHS":33,"HOLY_SHITS":0,"ITEM_TIMING":{"MEGA_HEALTH":5855,"RED_ARMOR":170,"YELLOW_ARMOR":850},"KILLS":55,"LOSE":1,"MATCH_GUID":"df8ddd67-91da-4ed6-8fe6-9e4b670a9bd2","MAX_STREAK":10,"MEDALS":{"ACCURACY":0,"ASSISTS":1,"CAPTURES":0,"COMBOKILL":3,"DEFENDS":15,"EXCELLENT":4,"FIRSTFRAG":0,"HEADSHOT":1,"HUMILIATION":0,"IMPRESSIVE":13,"MIDAIR":1,"PERFECT":0,"PERFORATED":0,"QUADGOD":0,"RAMPAGE":0,"REVENGE":3},"MODEL":"razor","NAME":"^1N^7utella^1E^7ater","NEUTRAL_FLAG_PICKUPS":0,"PICKUPS":{"AMMO":45,"ARMOR":26,"ARMOR_REGEN":0,"BATTLESUIT":0,"DOUBLER":0,"FLIGHT":0,"GREEN_ARMOR":0,"GUARD":0,"HASTE":0,"HEALTH":47,"INVIS":0,"INVULNERABILITY":0,"KAMIKAZE":0,"MEDKIT":0,"MEGA_HEALTH":5,"OTHER_HOLDABLE":0,"OTHER_POWERUP":0,"PORTAL":0,"QUAD":4,"RED_ARMOR":5,"REGEN":7,"SCOUT":0,"TELEPORTER":0,"YELLOW_ARMOR":2},"PLAY_TIME":1370,"QUIT":0,"RANK":3,"RED_FLAG_PICKUPS":4,"SCORE":313,"STEAM_ID":"76561197970786646","TEAM":2,"TEAM_JOIN_TIME":0,"TEAM_RANK":1,"TIED_RANK":0,"TIED_TEAM_RANK":0,"WARMUP":false,"WEAPONS":{"BFG":{"D":0,"DG":0,"DR":0,"H":0,"K":0,"P":0,"S":0,"T":0},"CHAINGUN":{"D":0,"DG":0,"DR":0,"H":0,"K":0,"P":0,"S":0,"T":0},"GAUNTLET":{"D":0,"DG":0,"DR":0,"H":0,"K":0,"P":0,"S":0,"T":0},"GRENADE":{"D":2,"DG":160,"DR":195,"H":2,"K":1,"P":21,"S":60,"T":83},"HMG":{"D":0,"DG":0,"DR":0,"H":0,"K":0,"P":0,"S":0,"T":0},"LIGHTNING":{"D":6,"DG":1320,"DR":865,"H":192,"K":6,"P":23,"S":579,"T":109},"MACHINEGUN":{"D":4,"DG":620,"DR":466,"H":124,"K":2,"P":0,"S":598,"T":396},"NAILGUN":{"D":0,"DG":0,"DR":0,"H":0,"K":0,"P":0,"S":0,"T":0},"OTHER_WEAPON":{"D":0,"DG":0,"DR":0,"H":0,"K":0,"P":0,"S":0,"T":0},"PLASMA":{"D":0,"DG":0,"DR":21,"H":0,"K":0,"P":10,"S":0,"T":0},"PROXMINE":{"D":0,"DG":0,"DR":0,"H":0,"K":0,"P":0,"S":0,"T":0},"RAILGUN":{"D":12,"DG":4400,"DR":2151,"H":49,"K":28,"P":43,"S":113,"T":318},"ROCKET":{"D":4,"DG":2468,"DR":933,"H":49,"K":11,"P":49,"S":135,"T":385},"SHOTGUN":{"D":5,"DG":675,"DR":1183,"H":139,"K":7,"P":24,"S":660,"T":76}},"WIN":0},{"ABORTED":false,"BLUE_FLAG_PICKUPS":4,"DAMAGE":{"DEALT":8557,"TAKEN":8368},"DEATHS":55,"HOLY_SHITS":0,"ITEM_TIMING":{"MEGA_HEALTH":5350,"RED_ARMOR":1552,"YELLOW_ARMOR":675},"KILLS":47,"LOSE":0,"MATCH_GUID":"df8ddd67-91da-4ed6-8fe6-9e4b670a9bd2","MAX_STREAK":6,"MEDALS":{"ACCURACY":0,"ASSISTS":0,"CAPTURES":1,"COMBOKILL":0,"DEFENDS":6,"EXCELLENT":1,"FIRSTFRAG":0,"HEADSHOT":3,"HUMILIATION":1,"IMPRESSIVE":12,"MIDAIR":0,"PERFECT":0,"PERFORATED":0,"QUADGOD":0,"RAMPAGE":0,"REVENGE":8},"MODEL":"ranger","NAME":"Mr B","NEUTRAL_FLAG_PICKUPS":0,"PICKUPS":{"AMMO":28,"ARMOR":83,"ARMOR_REGEN":0,"BATTLESUIT":0,"DOUBLER":0,"FLIGHT":0,"GREEN_ARMOR":0,"GUARD":0,"HASTE":1,"HEALTH":55,"INVIS":0,"INVULNERABILITY":0,"KAMIKAZE":0,"MEDKIT":0,"MEGA_HEALTH":1,"OTHER_HOLDABLE":0,"OTHER_POWERUP":0,"PORTAL":0,"QUAD":2,"RED_ARMOR":9,"REGEN":1,"SCOUT":0,"TELEPORTER":0,"YELLOW_ARMOR":2},"PLAY_TIME":1370,"QUIT":0,"RANK":4,"RED_FLAG_PICKUPS":0,"SCORE":289,"STEAM_ID":"76561198050521325","TEAM":1,"TEAM_JOIN_TIME":0,"TEAM_RANK":3,"TIED_RANK":0,"TIED_TEAM_RANK":0,"WARMUP":false,"WEAPONS":{"BFG":{"D":0,"DG":0,"DR":0,"H":0,"K":0,"P":0,"S":0,"T":0},"CHAINGUN":{"D":0,"DG":0,"DR":0,"H":0,"K":0,"P":0,"S":0,"T":0},"GAUNTLET":{"D":0,"DG":50,"DR":0,"H":0,"K":1,"P":0,"S":0,"T":2},"GRENADE":{"D":0,"DG":24,"DR":238,"H":1,"K":0,"P":24,"S":30,"T":49},"HMG":{"D":0,"DG":0,"DR":0,"H":0,"K":0,"P":0,"S":0,"T":0},"LIGHTNING":{"D":10,"DG":996,"DR":1434,"H":169,"K":4,"P":24,"S":511,"T":102},"MACHINEGUN":{"D":4,"DG":800,"DR":563,"H":160,"K":7,"P":0,"S":558,"T":514},"NAILGUN":{"D":0,"DG":0,"DR":0,"H":0,"K":0,"P":0,"S":0,"T":0},"OTHER_WEAPON":{"D":0,"DG":0,"DR":0,"H":0,"K":0,"P":0,"S":0,"T":0},"PLASMA":{"D":0,"DG":61,"DR":0,"H":4,"K":0,"P":2,"S":29,"T":14},"PROXMINE":{"D":0,"DG":0,"DR":0,"H":0,"K":0,"P":0,"S":0,"T":0},"RAILGUN":{"D":25,"DG":3920,"DR":3896,"H":45,"K":19,"P":53,"S":95,"T":356},"ROCKET":{"D":9,"DG":986,"DR":1237,"H":20,"K":5,"P":33,"S":52,"T":168},"SHOTGUN":{"D":7,"DG":1720,"DR":925,"H":283,"K":11,"P":25,"S":1200,"T":162}},"WIN":1},{"ABORTED":false,"BLUE_FLAG_PICKUPS":0,"DAMAGE":{"DEALT":10481,"TAKEN":7564},"DEATHS":36,"HOLY_SHITS":0,"ITEM_TIMING":{"MEGA_HEALTH":7850,"RED_ARMOR":5563,"YELLOW_ARMOR":6500},"KILLS":60,"LOSE":1,"MATCH_GUID":"df8ddd67-91da-4ed6-8fe6-9e4b670a9bd2","MAX_STREAK":11,"MEDALS":{"ACCURACY":0,"ASSISTS":0,"CAPTURES":1,"COMBOKILL":3,"DEFENDS":7,"EXCELLENT":5,"FIRSTFRAG":0,"HEADSHOT":1,"HUMILIATION":0,"IMPRESSIVE":27,"MIDAIR":0,"PERFECT":0,"PERFORATED":0,"QUADGOD":0,"RAMPAGE":0,"REVENGE":4},"MODEL":"slash/default","NAME":"wanxev","NEUTRAL_FLAG_PICKUPS":0,"PICKUPS":{"AMMO":26,"ARMOR":105,"ARMOR_REGEN":0,"BATTLESUIT":0,"DOUBLER":0,"FLIGHT":0,"GREEN_ARMOR":0,"GUARD":0,"HASTE":0,"HEALTH":48,"INVIS":0,"INVULNERABILITY":0,"KAMIKAZE":0,"MEDKIT":0,"MEGA_HEALTH":3,"OTHER_HOLDABLE":0,"OTHER_POWERUP":0,"PORTAL":0,"QUAD":0,"RED_ARMOR":9,"REGEN":4,"SCOUT":0,"TELEPORTER":0,"YELLOW_ARMOR":6},"PLAY_TIME":1370,"QUIT":0,"RANK":5,"RED_FLAG_PICKUPS":5,"SCORE":252,"STEAM_ID":"76561198257336657","TEAM":2,"TEAM_JOIN_TIME":0,"TEAM_RANK":2,"TIED_RANK":0,"TIED_TEAM_RANK":0,"WARMUP":false,"WEAPONS":{"BFG":{"D":0,"DG":0,"DR":0,"H":0,"K":0,"P":0,"S":0,"T":0},"CHAINGUN":{"D":0,"DG":0,"DR":0,"H":0,"K":0,"P":0,"S":0,"T":0},"GAUNTLET":{"D":0,"DG":0,"DR":0,"H":0,"K":0,"P":0,"S":0,"T":0},"GRENADE":{"D":0,"DG":0,"DR":31,"H":0,"K":0,"P":23,"S":11,"T":21},"HMG":{"D":0,"DG":0,"DR":0,"H":0,"K":0,"P":0,"S":0,"T":0},"LIGHTNING":{"D":5,"DG":2352,"DR":1634,"H":403,"K":15,"P":28,"S":1036,"T":216},"MACHINEGUN":{"D":2,"DG":250,"DR":264,"H":52,"K":2,"P":0,"S":308,"T":404},"NAILGUN":{"D":0,"DG":0,"DR":0,"H":0,"K":0,"P":0,"S":0,"T":0},"OTHER_WEAPON":{"D":0,"DG":0,"DR":0,"H":0,"K":0,"P":0,"S":0,"T":0},"PLASMA":{"D":0,"DG":0,"DR":0,"H":0,"K":0,"P":2,"S":0,"T":0},"PROXMINE":{"D":0,"DG":0,"DR":0,"H":0,"K":0,"P":0,"S":0,"T":0},"RAILGUN":{"D":23,"DG":7600,"DR":4023,"H":94,"K":41,"P":42,"S":179,"T":523},"ROCKET":{"D":3,"DG":279,"DR":1220,"H":14,"K":2,"P":29,"S":61,"T":190},"SHOTGUN":{"D":2,"DG":0,"DR":291,"H":0,"K":0,"P":6,"S":60,"T":12}},"WIN":0},{"ABORTED":false,"BLUE_FLAG_PICKUPS":3,"DAMAGE":{"DEALT":7369,"TAKEN":8687},"DEATHS":56,"HOLY_SHITS":0,"ITEM_TIMING":{"MEGA_HEALTH":3625,"RED_ARMOR":2650,"YELLOW_ARMOR":9591},"KILLS":30,"LOSE":0,"MATCH_GUID":"df8ddd67-91da-4ed6-8fe6-9e4b670a9bd2","MAX_STREAK":2,"MEDALS":{"ACCURACY":0,"ASSISTS":1,"CAPTURES":0,"COMBOKILL":0,"DEFENDS":6,"EXCELLENT":0,"FIRSTFRAG":0,"HEADSHOT":0,"HUMILIATION":0,"IMPRESSIVE":6,"MIDAIR":0,"PERFECT":0,"PERFORATED":0,"QUADGOD":0,"RAMPAGE":0,"REVENGE":7},"MODEL":"sarge","NAME":"^1oMg^7 Bforce","NEUTRAL_FLAG_PICKUPS":0,"PICKUPS":{"AMMO":15,"ARMOR":33,"ARMOR_REGEN":0,"BATTLESUIT":0,"DOUBLER":0,"FLIGHT":0,"GREEN_ARMOR":0,"GUARD":0,"HASTE":2,"HEALTH":36,"INVIS":0,"INVULNERABILITY":0,"KAMIKAZE":0,"MEDKIT":0,"MEGA_HEALTH":1,"OTHER_HOLDABLE":0,"OTHER_POWERUP":0,"PORTAL":0,"QUAD":2,"RED_ARMOR":5,"REGEN":6,"SCOUT":0,"TELEPORTER":0,"YELLOW_ARMOR":12},"PLAY_TIME":1370,"QUIT":0,"RANK":6,"RED_FLAG_PICKUPS":0,"SCORE":220,"STEAM_ID":"76561198257425756","TEAM":1,"TEAM_JOIN_TIME":0,"TEAM_RANK":4,"TIED_RANK":0,"TIED_TEAM_RANK":0,"WARMUP":false,"WEAPONS":{"BFG":{"D":0,"DG":0,"DR":0,"H":0,"K":0,"P":0,"S":0,"T":0},"CHAINGUN":{"D":0,"DG":0,"DR":0,"H":0,"K":0,"P":0,"S":0,"T":0},"GAUNTLET":{"D":0,"DG":0,"DR":0,"H":0,"K":0,"P":0,"S":0,"T":0},"GRENADE":{"D":0,"DG":59,"DR":0,"H":2,"K":0,"P":11,"S":9,"T":11},"HMG":{"D":0,"DG":0,"DR":0,"H":0,"K":0,"P":0,"S":0,"T":0},"LIGHTNING":{"D":9,"DG":1554,"DR":1590,"H":247,"K":8,"P":30,"S":1022,"T":158},"MACHINEGUN":{"D":3,"DG":625,"DR":476,"H":125,"K":2,"P":0,"S":609,"T":514},"NAILGUN":{"D":0,"DG":0,"DR":0,"H":0,"K":0,"P":0,"S":0,"T":0},"OTHER_WEAPON":{"D":0,"DG":0,"DR":0,"H":0,"K":0,"P":0,"S":0,"T":0},"PLASMA":{"D":1,"DG":0,"DR":19,"H":0,"K":0,"P":5,"S":0,"T":0},"PROXMINE":{"D":0,"DG":0,"DR":0,"H":0,"K":0,"P":0,"S":0,"T":0},"RAILGUN":{"D":24,"DG":2800,"DR":3657,"H":35,"K":12,"P":31,"S":93,"T":347},"ROCKET":{"D":8,"DG":1541,"DR":1789,"H":36,"K":2,"P":45,"S":125,"T":245},"SHOTGUN":{"D":11,"DG":790,"DR":1112,"H":156,"K":6,"P":17,"S":760,"T":93}},"WIN":1},{"ABORTED":false,"BLUE_FLAG_PICKUPS":0,"DAMAGE":{"DEALT":7796,"TAKEN":6727},"DEATHS":46,"HOLY_SHITS":0,"ITEM_TIMING":{"RED_ARMOR":1850,"YELLOW_ARMOR":4766},"KILLS":33,"LOSE":1,"MATCH_GUID":"df8ddd67-91da-4ed6-8fe6-9e4b670a9bd2","MAX_STREAK":6,"MEDALS":{"ACCURACY":0,"ASSISTS":0,"CAPTURES":0,"COMBOKILL":1,"DEFENDS":1,"EXCELLENT":2,"FIRSTFRAG":0,"HEADSHOT":0,"HUMILIATION":0,"IMPRESSIVE":8,"MIDAIR":0,"PERFECT":0,"PERFORATED":0,"QUADGOD":0,"RAMPAGE":0,"REVENGE":6},"MODEL":"sarge","NAME":"odin","NEUTRAL_FLAG_PICKUPS":0,"PICKUPS":{"AMMO":49,"ARMOR":111,"ARMOR_REGEN":0,"BATTLESUIT":0,"DOUBLER":0,"FLIGHT":0,"GREEN_ARMOR":0,"GUARD":0,"HASTE":0,"HEALTH":58,"INVIS":0,"INVULNERABILITY":0,"KAMIKAZE":0,"MEDKIT":0,"MEGA_HEALTH":0,"OTHER_HOLDABLE":0,"OTHER_POWERUP":0,"PORTAL":0,"QUAD":0,"RED_ARMOR":1,"REGEN":0,"SCOUT":0,"TELEPORTER":0,"YELLOW_ARMOR":6},"PLAY_TIME":1370,"QUIT":0,"RANK":7,"RED_FLAG_PICKUPS":6,"SCORE":182,"STEAM_ID":"76561198113333992","TEAM":2,"TEAM_JOIN_TIME":0,"TEAM_RANK":3,"TIED_RANK":0,"TIED_TEAM_RANK":0,"WARMUP":false,"WEAPONS":{"BFG":{"D":0,"DG":0,"DR":0,"H":0,"K":0,"P":0,"S":0,"T":0},"CHAINGUN":{"D":0,"DG":0,"DR":0,"H":0,"K":0,"P":0,"S":0,"T":0},"GAUNTLET":{"D":0,"DG":0,"DR":0,"H":0,"K":0,"P":0,"S":0,"T":0},"GRENADE":{"D":1,"DG":100,"DR":93,"H":1,"K":0,"P":26,"S":26,"T":28},"HMG":{"D":0,"DG":0,"DR":0,"H":0,"K":0,"P":0,"S":0,"T":0},"LIGHTNING":{"D":13,"DG":1074,"DR":1406,"H":185,"K":5,"P":17,"S":682,"T":121},"MACHINEGUN":{"D":4,"DG":690,"DR":583,"H":139,"K":3,"P":0,"S":458,"T":504},"NAILGUN":{"D":0,"DG":0,"DR":0,"H":0,"K":0,"P":0,"S":0,"T":0},"OTHER_WEAPON":{"D":0,"DG":0,"DR":0,"H":0,"K":0,"P":0,"S":0,"T":0},"PLASMA":{"D":0,"DG":0,"DR":40,"H":0,"K":0,"P":2,"S":0,"T":0},"PROXMINE":{"D":0,"DG":0,"DR":0,"H":0,"K":0,"P":0,"S":0,"T":0},"RAILGUN":{"D":14,"DG":2160,"DR":2381,"H":26,"K":12,"P":29,"S":45,"T":182},"ROCKET":{"D":9,"DG":2507,"DR":1210,"H":52,"K":7,"P":44,"S":171,"T":405},"SHOTGUN":{"D":5,"DG":1265,"DR":939,"H":258,"K":6,"P":17,"S":960,"T":127}},"WIN":0},{"ABORTED":false,"BLUE_FLAG_PICKUPS":2,"DAMAGE":{"DEALT":7072,"TAKEN":7623},"DEATHS":56,"HOLY_SHITS":0,"ITEM_TIMING":{"RED_ARMOR":2308,"YELLOW_ARMOR":3767},"KILLS":31,"LOSE":0,"MATCH_GUID":"df8ddd67-91da-4ed6-8fe6-9e4b670a9bd2","MAX_STREAK":4,"MEDALS":{"ACCURACY":0,"ASSISTS":0,"CAPTURES":0,"COMBOKILL":2,"DEFENDS":4,"EXCELLENT":2,"FIRSTFRAG":0,"HEADSHOT":2,"HUMILIATION":2,"IMPRESSIVE":4,"MIDAIR":0,"PERFECT":0,"PERFORATED":0,"QUADGOD":0,"RAMPAGE":0,"REVENGE":6},"MODEL":"Uriel","NAME":"Ozo","NEUTRAL_FLAG_PICKUPS":0,"PICKUPS":{"AMMO":29,"ARMOR":1,"ARMOR_REGEN":0,"BATTLESUIT":0,"DOUBLER":0,"FLIGHT":0,"GREEN_ARMOR":0,"GUARD":0,"HASTE":1,"HEALTH":24,"INVIS":0,"INVULNERABILITY":0,"KAMIKAZE":0,"MEDKIT":0,"MEGA_HEALTH":0,"OTHER_HOLDABLE":0,"OTHER_POWERUP":0,"PORTAL":0,"QUAD":0,"RED_ARMOR":3,"REGEN":2,"SCOUT":0,"TELEPORTER":0,"YELLOW_ARMOR":7},"PLAY_TIME":1370,"QUIT":0,"RANK":8,"RED_FLAG_PICKUPS":0,"SCORE":178,"STEAM_ID":"76561198256217116","TEAM":1,"TEAM_JOIN_TIME":0,"TEAM_RANK":5,"TIED_RANK":0,"TIED_TEAM_RANK":0,"WARMUP":false,"WEAPONS":{"BFG":{"D":0,"DG":0,"DR":0,"H":0,"K":0,"P":0,"S":0,"T":0},"CHAINGUN":{"D":0,"DG":0,"DR":0,"H":0,"K":0,"P":0,"S":0,"T":0},"GAUNTLET":{"D":0,"DG":150,"DR":50,"H":0,"K":2,"P":0,"S":0,"T":12},"GRENADE":{"D":2,"DG":371,"DR":67,"H":8,"K":3,"P":16,"S":90,"T":100},"HMG":{"D":0,"DG":0,"DR":0,"H":0,"K":0,"P":0,"S":0,"T":0},"LIGHTNING":{"D":10,"DG":894,"DR":1662,"H":149,"K":3,"P":15,"S":557,"T":95},"MACHINEGUN":{"D":1,"DG":510,"DR":470,"H":103,"K":2,"P":0,"S":492,"T":543},"NAILGUN":{"D":0,"DG":0,"DR":0,"H":0,"K":0,"P":0,"S":0,"T":0},"OTHER_WEAPON":{"D":0,"DG":0,"DR":0,"H":0,"K":0,"P":0,"S":0,"T":0},"PLASMA":{"D":0,"DG":0,"DR":0,"H":0,"K":0,"P":0,"S":0,"T":0},"PROXMINE":{"D":0,"DG":0,"DR":0,"H":0,"K":0,"P":0,"S":0,"T":0},"RAILGUN":{"D":26,"DG":1600,"DR":2933,"H":20,"K":5,"P":27,"S":55,"T":171},"ROCKET":{"D":13,"DG":2092,"DR":1997,"H":42,"K":10,"P":39,"S":129,"T":295},"SHOTGUN":{"D":4,"DG":1455,"DR":429,"H":293,"K":6,"P":25,"S":1400,"T":150}},"WIN":1},{"ABORTED":false,"BLUE_FLAG_PICKUPS":0,"DAMAGE":{"DEALT":6113,"TAKEN":6879},"DEATHS":48,"HOLY_SHITS":0,"ITEM_TIMING":{"MEGA_HEALTH":22825,"RED_ARMOR":708,"YELLOW_ARMOR":6320},"KILLS":34,"LOSE":1,"MATCH_GUID":"df8ddd67-91da-4ed6-8fe6-9e4b670a9bd2","MAX_STREAK":5,"MEDALS":{"ACCURACY":0,"ASSISTS":0,"CAPTURES":0,"COMBOKILL":2,"DEFENDS":9,"EXCELLENT":0,"FIRSTFRAG":0,"HEADSHOT":0,"HUMILIATION":0,"IMPRESSIVE":4,"MIDAIR":0,"PERFECT":0,"PERFORATED":0,"QUADGOD":0,"RAMPAGE":0,"REVENGE":6},"MODEL":"ranger/blue","NAME":"^4BlacK ScoRPioN^7","NEUTRAL_FLAG_PICKUPS":0,"PICKUPS":{"AMMO":33,"ARMOR":34,"ARMOR_REGEN":0,"BATTLESUIT":0,"DOUBLER":0,"FLIGHT":0,"GREEN_ARMOR":0,"GUARD":0,"HASTE":3,"HEALTH":22,"INVIS":0,"INVULNERABILITY":0,"KAMIKAZE":0,"MEDKIT":0,"MEGA_HEALTH":2,"OTHER_HOLDABLE":0,"OTHER_POWERUP":0,"PORTAL":0,"QUAD":2,"RED_ARMOR":3,"REGEN":3,"SCOUT":0,"TELEPORTER":0,"YELLOW_ARMOR":15},"PLAY_TIME":1370,"QUIT":0,"RANK":9,"RED_FLAG_PICKUPS":1,"SCORE":141,"STEAM_ID":"76561198257374234","TEAM":2,"TEAM_JOIN_TIME":0,"TEAM_RANK":4,"TIED_RANK":0,"TIED_TEAM_RANK":0,"WARMUP":false,"WEAPONS":{"BFG":{"D":0,"DG":0,"DR":0,"H":0,"K":0,"P":0,"S":0,"T":0},"CHAINGUN":{"D":0,"DG":0,"DR":0,"H":0,"K":0,"P":0,"S":0,"T":0},"GAUNTLET":{"D":3,"DG":50,"DR":177,"H":0,"K":0,"P":0,"S":0,"T":15},"GRENADE":{"D":0,"DG":38,"DR":42,"H":1,"K":0,"P":9,"S":19,"T":19},"HMG":{"D":0,"DG":0,"DR":0,"H":0,"K":0,"P":0,"S":0,"T":0},"LIGHTNING":{"D":8,"DG":1434,"DR":1073,"H":248,"K":7,"P":19,"S":1023,"T":169},"MACHINEGUN":{"D":4,"DG":235,"DR":979,"H":47,"K":0,"P":0,"S":244,"T":450},"NAILGUN":{"D":0,"DG":0,"DR":0,"H":0,"K":0,"P":0,"S":0,"T":0},"OTHER_WEAPON":{"D":0,"DG":0,"DR":0,"H":0,"K":0,"P":0,"S":0,"T":0},"PLASMA":{"D":0,"DG":20,"DR":0,"H":1,"K":1,"P":2,"S":61,"T":19},"PROXMINE":{"D":0,"DG":0,"DR":0,"H":0,"K":0,"P":0,"S":0,"T":0},"RAILGUN":{"D":11,"DG":2240,"DR":2082,"H":28,"K":11,"P":37,"S":87,"T":370},"ROCKET":{"D":10,"DG":1026,"DR":1442,"H":26,"K":5,"P":33,"S":92,"T":182},"SHOTGUN":{"D":12,"DG":1070,"DR":959,"H":209,"K":10,"P":30,"S":1020,"T":142}},"WIN":0},{"ABORTED":false,"BLUE_FLAG_PICKUPS":0,"DAMAGE":{"DEALT":5910,"TAKEN":5896},"DEATHS":39,"HOLY_SHITS":0,"ITEM_TIMING":{"YELLOW_ARMOR":4604},"KILLS":33,"LOSE":1,"MATCH_GUID":"df8ddd67-91da-4ed6-8fe6-9e4b670a9bd2","MAX_STREAK":5,"MEDALS":{"ACCURACY":0,"ASSISTS":0,"CAPTURES":0,"COMBOKILL":0,"DEFENDS":5,"EXCELLENT":0,"FIRSTFRAG":0,"HEADSHOT":0,"HUMILIATION":0,"IMPRESSIVE":5,"MIDAIR":0,"PERFECT":0,"PERFORATED":0,"QUADGOD":0,"RAMPAGE":0,"REVENGE":3},"MODEL":"mynx/bright","NAME":"^6 RIRI NO HOMO^7","NEUTRAL_FLAG_PICKUPS":0,"PICKUPS":{"AMMO":32,"ARMOR":56,"ARMOR_REGEN":0,"BATTLESUIT":0,"DOUBLER":0,"FLIGHT":0,"GREEN_ARMOR":0,"GUARD":0,"HASTE":0,"HEALTH":37,"INVIS":0,"INVULNERABILITY":0,"KAMIKAZE":0,"MEDKIT":0,"MEGA_HEALTH":0,"OTHER_HOLDABLE":0,"OTHER_POWERUP":0,"PORTAL":0,"QUAD":1,"RED_ARMOR":0,"REGEN":3,"SCOUT":0,"TELEPORTER":0,"YELLOW_ARMOR":6},"PLAY_TIME":1368,"QUIT":0,"RANK":10,"RED_FLAG_PICKUPS":0,"SCORE":131,"STEAM_ID":"76561198257496197","TEAM":2,"TEAM_JOIN_TIME":0,"TEAM_RANK":5,"TIED_RANK":0,"TIED_TEAM_RANK":0,"WARMUP":false,"WEAPONS":{"BFG":{"D":0,"DG":0,"DR":0,"H":0,"K":0,"P":0,"S":0,"T":0},"CHAINGUN":{"D":0,"DG":0,"DR":0,"H":0,"K":0,"P":0,"S":0,"T":0},"GAUNTLET":{"D":0,"DG":0,"DR":0,"H":0,"K":0,"P":0,"S":0,"T":0},"GRENADE":{"D":0,"DG":56,"DR":14,"H":2,"K":0,"P":13,"S":15,"T":19},"HMG":{"D":0,"DG":0,"DR":0,"H":0,"K":0,"P":0,"S":0,"T":0},"LIGHTNING":{"D":5,"DG":480,"DR":1205,"H":82,"K":3,"P":25,"S":301,"T":122},"MACHINEGUN":{"D":3,"DG":375,"DR":470,"H":77,"K":3,"P":0,"S":337,"T":536},"NAILGUN":{"D":0,"DG":0,"DR":0,"H":0,"K":0,"P":0,"S":0,"T":0},"OTHER_WEAPON":{"D":0,"DG":0,"DR":0,"H":0,"K":0,"P":0,"S":0,"T":0},"PLASMA":{"D":0,"DG":0,"DR":0,"H":0,"K":0,"P":2,"S":0,"T":0},"PROXMINE":{"D":0,"DG":0,"DR":0,"H":0,"K":0,"P":0,"S":0,"T":0},"RAILGUN":{"D":17,"DG":2320,"DR":1786,"H":29,"K":9,"P":37,"S":69,"T":239},"ROCKET":{"D":8,"DG":2039,"DR":1066,"H":45,"K":12,"P":30,"S":136,"T":360},"SHOTGUN":{"D":6,"DG":640,"DR":1220,"H":103,"K":6,"P":17,"S":420,"T":89}},"WIN":0}]}